Workbook

Sheet archigos 8.0
A1: Unnamed: 0 | B1: obsid | C1: leadid | D1: ccode | E1: idacr | F1: country | G1: continent | H1: leader | I1: startdate | J1: startdate_new | K1: enddate | L1: enddate_new | M1: entry | N1: exit | O1: exitcode | P1: prevtimesinoffice | Q1: posttenurefate | R1: gender | S1: yrborn | T1: yrdied | U1: borndate | V1: ebirthdate | W1: deathdate | X1: edeathdate | Y1: dbpediauri | Z1: numentry | AA1: numexit | AB1: numexitcode | AC1: numposttenurefate | AD1: fties | AE1: ftcur | AF1: start_year | AG1: end_year | AH1: avg_gdp_growth | AI1: avg_gni_per_capita | AJ1: avg_inflation_rate | AK1: avg_child_mortality_rate | AL1: avg_population_growth_rate | AM1: avg_natural_resource_rents | AN1: polity_mean | AO1: was_colonized | AP1: colonial_power | AQ1: colonial_begin | AR1: colonial_end | AS1: colonial_duration | AT1: tenure_days | AU1: tenure_years
A2: 0 | B2: USA-1869 | C2: 81dcc176-1e42-11e4-b4cd-db5882bf8def | D2: 2 | E2: USA | F2: =VLOOKUP(E2,country_continent!A:C,2,FALSE) -> United States of America | G2: =VLOOKUP(E2,country_continent!A:C,3,FALSE) -> North America | H2: Grant | I2: 1869-03-04 | J2: =IF(ISNUMBER(SEARCH("-", I2)), SUBSTITUTE(I2, "-", "/"), I2) -> 1869/03/04 | K2: 1877-03-04 | L2: =IF(ISNUMBER(SEARCH("-", K2)), SUBSTITUTE(K2, "-", "/"), K2) -> 1877/03/04 | M2: Regular | N2: Regular | O2: Regular | P2: 0 | Q2: OK | R2: M | S2: 1822 | T2: 1885 | W2: 1885-07-23 | X2: 23jul1885 | Y2: https://urldefense.proofpoint.com/v2/url?u=http-3A__dbpedia.org_resource_Ulysses-5FS.-5FGrant&d=BQID-g&c=kbmfwr1Yojg42sGEpaQh5ofMHBeTl9EI2eaqQZhHbOU&r=ZliGVSRwfirWoETOrKCh2RSnoygzVPWEk95Me9L-Kwo&m=EaKyFx9mpkhPdFxsxzvW_fiM3jbYwM3xYLjVbSFoDAg&s=x7yRI4mbwG8b0j8c_AwqAahtkPcCfIY2uH8tdRaReBw&e= | Z2: 0 | AA2: 1 | AB2: 0 | AC2: 0 | AF2: 1869 | AG2: 1877 | AO2: FALSE | AT2: 2922 | AU2: =ROUND(AT2/365,3) -> 8.005
A3: 1 | B3: USA-1877 | C3: 81dcc177-1e42-11e4-b4cd-db5882bf8def | D3: 2 | E3: USA | F3: =VLOOKUP(E3,country_continent!A:C,2,FALSE) -> United States of America | G3: =VLOOKUP(E3,country_continent!A:C,3,FALSE) -> North America | H3: Hayes | I3: 1877-03-04 | J3: =IF(ISNUMBER(SEARCH("-", I3)), SUBSTITUTE(I3, "-", "/"), I3) -> 1877/03/04 | K3: 1881-03-04 | L3: =IF(ISNUMBER(SEARCH("-", K3)), SUBSTITUTE(K3, "-", "/"), K3) -> 1881/03/04 | M3: Regular | N3: Regular | O3: Regular | P3: 0 | Q3: OK | R3: M | S3: 1822 | T3: 1893 | W3: 1893-01-17 | X3: 17jan1893 | Y3: https://urldefense.proofpoint.com/v2/url?u=http-3A__dbpedia.org_resource_Rutherford-5FB.-5FHayes&d=BQID-g&c=kbmfwr1Yojg42sGEpaQh5ofMHBeTl9EI2eaqQZhHbOU&r=ZliGVSRwfirWoETOrKCh2RSnoygzVPWEk95Me9L-Kwo&m=EaKyFx9mpkhPdFxsxzvW_fiM3jbYwM3xYLjVbSFoDAg&s=8oshcxB52W-Pg-2a6AvRVJEYMU-S-RG55-369eJ-PyY&e= | Z3: 0 | AA3: 1 | AB3: 0 | AC3: 0 | AF3: 1877 | AG3: 1881 | AO3: FALSE | AT3: 1461 | AU3: =ROUND(AT3/365,3) -> 4.003
A4: 2 | B4: USA-1881-1 | C4: 81dcf24a-1e42-11e4-b4cd-db5882bf8def | D4: 2 | E4: USA | F4: =VLOOKUP(E4,country_continent!A:C,2,FALSE) -> United States of America | G4: =VLOOKUP(E4,country_continent!A:C,3,FALSE) -> North America | H4: Garfield | I4: 1881-03-04 | J4: =IF(ISNUMBER(SEARCH("-", I4)), SUBSTITUTE(I4, "-", "/"), I4) -> 1881/03/04 | K4: 1881-09-19 | L4: =IF(ISNUMBER(SEARCH("-", K4)), SUBSTITUTE(K4, "-", "/"), K4) -> 1881/09/19 | M4: Regular | N4: Irregular | O4: Assassination by Unsupported Individual | P4: 0 | Q4: Death | R4: M | S4: 1831 | T4: 1881 | W4: 1881-09-19 | X4: 19sep1881 | Y4: https://urldefense.proofpoint.com/v2/url?u=http-3A__dbpedia.org_resource_James-5FA.-5FGarfield&d=BQID-g&c=kbmfwr1Yojg42sGEpaQh5ofMHBeTl9EI2eaqQZhHbOU&r=ZliGVSRwfirWoETOrKCh2RSnoygzVPWEk95Me9L-Kwo&m=EaKyFx9mpkhPdFxsxzvW_fiM3jbYwM3xYLjVbSFoDAg&s=qTPSlRS-mPD_m8ZM3luuJ4W47DtmOPoXSnSZn-lYsqM&e= | Z4: 0 | AA4: 3 | AB4: 11 | AC4: 3 | AF4: 1881 | AG4: 1881 | AO4: FALSE | AT4: 199 | AU4: =ROUND(AT4/365,3) -> 0.545
A5: 3 | B5: USA-1881-2 | C5: 81dcf24b-1e42-11e4-b4cd-db5882bf8def | D5: 2 | E5: USA | F5: =VLOOKUP(E5,country_continent!A:C,2,FALSE) -> United States of America | G5: =VLOOKUP(E5,country_continent!A:C,3,FALSE) -> North America | H5: Arthur | I5: 1881-09-19 | J5: =IF(ISNUMBER(SEARCH("-", I5)), SUBSTITUTE(I5, "-", "/"), I5) -> 1881/09/19 | K5: 1885-03-04 | L5: =IF(ISNUMBER(SEARCH("-", K5)), SUBSTITUTE(K5, "-", "/"), K5) -> 1885/03/04 | M5: Regular | N5: Regular | O5: Regular | P5: 0 | Q5: OK | R5: M | S5: 1829 | T5: 1886 | W5: 1886-11-18 | X5: 18nov1886 | Y5: https://urldefense.proofpoint.com/v2/url?u=http-3A__dbpedia.org_resource_Chester-5FA.-5FArthur&d=BQID-g&c=kbmfwr1Yojg42sGEpaQh5ofMHBeTl9EI2eaqQZhHbOU&r=ZliGVSRwfirWoETOrKCh2RSnoygzVPWEk95Me9L-Kwo&m=EaKyFx9mpkhPdFxsxzvW_fiM3jbYwM3xYLjVbSFoDAg&s=XiglK4IJ3ZCC1kR4Hmb8eVB-V7A0tQprCtTKzOl42YM&e= | Z5: 0 | AA5: 1 | AB5: 0 | AC5: 0 | AF5: 1881 | AG5: 1885 | AO5: FALSE | AT5: 1262 | AU5: =ROUND(AT5/365,3) -> 3.458
A6: 4 | B6: USA-1885 | C6: 34fb1558-3bbd-11e5-afeb-eb6f07f9fec7 | D6: 2 | E6: USA | F6: =VLOOKUP(E6,country_continent!A:C,2,FALSE) -> United States of America | G6: =VLOOKUP(E6,country_continent!A:C,3,FALSE) -> North America | H6: Cleveland | I6: 1885-03-04 | J6: =IF(ISNUMBER(SEARCH("-", I6)), SUBSTITUTE(I6, "-", "/"), I6) -> 1885/03/04 | K6: 1889-03-04 | L6: =IF(ISNUMBER(SEARCH("-", K6)), SUBSTITUTE(K6, "-", "/"), K6) -> 1889/03/04 | M6: Regular | N6: Regular | O6: Regular | P6: 0 | Q6: OK | R6: M | S6: 1837 | T6: 1908 | W6: 3098 | X6: 3098 | Y6: https://urldefense.proofpoint.com/v2/url?u=http-3A__dbpedia.org_resource_Grover-5FCleveland&d=BQID-g&c=kbmfwr1Yojg42sGEpaQh5ofMHBeTl9EI2eaqQZhHbOU&r=ZliGVSRwfirWoETOrKCh2RSnoygzVPWEk95Me9L-Kwo&m=EaKyFx9mpkhPdFxsxzvW_fiM3jbYwM3xYLjVbSFoDAg&s=BH6RahZV58hS1fIGz1muHnQkbAirSz4Yy2wc6chejsQ&e= | Z6: 0 | AA6: 1 | AB6: 0 | AC6: 0 | AF6: 1885 | AG6: 1889 | AO6: FALSE | AT6: 1461 | AU6: =ROUND(AT6/365,3) -> 4.003
A7: 5 | B7: USA-1889 | C7: 81dcf24d-1e42-11e4-b4cd-db5882bf8def | D7: 2 | E7: USA | F7: =VLOOKUP(E7,country_continent!A:C,2,FALSE) -> United States of America | G7: =VLOOKUP(E7,country_continent!A:C,3,FALSE) -> North America | H7: Harrison | I7: 1889-03-04 | J7: =IF(ISNUMBER(SEARCH("-", I7)), SUBSTITUTE(I7, "-", "/"), I7) -> 1889/03/04 | K7: 1893-03-04 | L7: =IF(ISNUMBER(SEARCH("-", K7)), SUBSTITUTE(K7, "-", "/"), K7) -> 1893/03/04 | M7: Regular | N7: Regular | O7: Regular | P7: 0 | Q7: OK | R7: M | S7: 1833 | T7: 1901 | W7: 438 | X7: 438 | Y7: https://urldefense.proofpoint.com/v2/url?u=http-3A__dbpedia.org_resource_Benjamin-5FHarrison&d=BQID-g&c=kbmfwr1Yojg42sGEpaQh5ofMHBeTl9EI2eaqQZhHbOU&r=ZliGVSRwfirWoETOrKCh2RSnoygzVPWEk95Me9L-Kwo&m=EaKyFx9mpkhPdFxsxzvW_fiM3jbYwM3xYLjVbSFoDAg&s=MA-TUrYNLJuZ9PTyDnsCkyBUtUyUkXWBHX7_p3f3pnA&e= | Z7: 0 | AA7: 1 | AB7: 0 | AC7: 0 | AF7: 1889 | AG7: 1893 | AO7: FALSE | AT7: 1461 | AU7: =ROUND(AT7/365,3) -> 4.003
A8: 6 | B8: USA-1893 | C8: 34fb1558-3bbd-11e5-afeb-eb6f07f9fec7 | D8: 2 | E8: USA | F8: =VLOOKUP(E8,country_continent!A:C,2,FALSE) -> United States of America | G8: =VLOOKUP(E8,country_continent!A:C,3,FALSE) -> North America | H8: Cleveland | I8: 1893-03-04 | J8: =IF(ISNUMBER(SEARCH("-", I8)), SUBSTITUTE(I8, "-", "/"), I8) -> 1893/03/04 | K8: 1897-03-04 | L8: =IF(ISNUMBER(SEARCH("-", K8)), SUBSTITUTE(K8, "-", "/"), K8) -> 1897/03/04 | M8: Regular | N8: Regular | O8: Regular | P8: 1 | Q8: OK | R8: M | S8: 1837 | T8: 1908 | W8: 3098 | X8: 3098 | Y8: https://urldefense.proofpoint.com/v2/url?u=http-3A__dbpedia.org_resource_Grover-5FCleveland&d=BQID-g&c=kbmfwr1Yojg42sGEpaQh5ofMHBeTl9EI2eaqQZhHbOU&r=ZliGVSRwfirWoETOrKCh2RSnoygzVPWEk95Me9L-Kwo&m=EaKyFx9mpkhPdFxsxzvW_fiM3jbYwM3xYLjVbSFoDAg&s=BH6RahZV58hS1fIGz1muHnQkbAirSz4Yy2wc6chejsQ&e= | Z8: 0 | AA8: 1 | AB8: 0 | AC8: 0 | AF8: 1893 | AG8: 1897 | AO8: FALSE | AT8: 1461 | AU8: =ROUND(AT8/365,3) -> 4.003
A9: 7 | B9: USA-1897 | C9: 81dcf24e-1e42-11e4-b4cd-db5882bf8def | D9: 2 | E9: USA | F9: =VLOOKUP(E9,country_continent!A:C,2,FALSE) -> United States of America | G9: =VLOOKUP(E9,country_continent!A:C,3,FALSE) -> North America | H9: McKinley | I9: 1897-03-04 | J9: =IF(ISNUMBER(SEARCH("-", I9)), SUBSTITUTE(I9, "-", "/"), I9) -> 1897/03/04 | K9: 623 | L9: =IF(ISNUMBER(SEARCH("-", K9)), SUBSTITUTE(K9, "-", "/"), K9) -> 623 | M9: Regular | N9: Irregular | O9: Assassination by Unsupported Individual | P9: 0 | Q9: Death | R9: M | S9: 1843 | T9: 1901 | W9: 623 | X9: 623 | Y9: https://urldefense.proofpoint.com/v2/url?u=http-3A__dbpedia.org_resource_William-5FMcKinley&d=BQID-g&c=kbmfwr1Yojg42sGEpaQh5ofMHBeTl9EI2eaqQZhHbOU&r=ZliGVSRwfirWoETOrKCh2RSnoygzVPWEk95Me9L-Kwo&m=EaKyFx9mpkhPdFxsxzvW_fiM3jbYwM3xYLjVbSFoDAg&s=c1fTbGMfG49MP3oJebg3Hp83_F7aiBUUfKgnhRd8AWs&e= | Z9: 0 | AA9: 3 | AB9: 11 | AC9: 3 | AF9: 1897 | AG9: 1901 | AO9: FALSE | AT9: 1654 | AU9: =ROUND(AT9/365,3) -> 4.532
A10: 8 | B10: USA-1901 | C10: 81dd231e-1e42-11e4-b4cd-db5882bf8def | D10: 2 | E10: USA | F10: =VLOOKUP(E10,country_continent!A:C,2,FALSE) -> United States of America | G10: =VLOOKUP(E10,country_continent!A:C,3,FALSE) -> North America | H10: Roosevelt, T. | I10: 623 | J10: =IF(ISNUMBER(SEARCH("-", I10)), SUBSTITUTE(I10, "-", "/"), I10) -> 623 | K10: 3351 | L10: =IF(ISNUMBER(SEARCH("-", K10)), SUBSTITUTE(K10, "-", "/"), K10) -> 3351 | M10: Regular | N10: Regular | O10: Regular | P10: 0 | Q10: OK | R10: M | S10: 1858 | T10: 1919 | Y10: https://urldefense.proofpoint.com/v2/url?u=http-3A__dbpedia.org_resource_Theodore-5FRoosevelt&d=BQID-g&c=kbmfwr1Yojg42sGEpaQh5ofMHBeTl9EI2eaqQZhHbOU&r=ZliGVSRwfirWoETOrKCh2RSnoygzVPWEk95Me9L-Kwo&m=EaKyFx9mpkhPdFxsxzvW_fiM3jbYwM3xYLjVbSFoDAg&s=mdUxrnAfyEPLl3hgYW-m-YrEL1hVsBHltrXf6_VHzrA&e= | Z10: 0 | AA10: 1 | AB10: 0 | AC10: 0 | AD10: Uncle (distant) of Roosevelt, F.%81dd53f3-1e42-11e4-b4cd-db5882bf8def | AE10: 0 | AF10: 1901 | AG10: 1909 | AO10: FALSE | AT10: 2728 | AU10: =ROUND(AT10/365,3) -> 7.474
A11: 9 | B11: USA-1909 | C11: 81dd231f-1e42-11e4-b4cd-db5882bf8def | D11: 2 | E11: USA | F11: =VLOOKUP(E11,country_continent!A:C,2,FALSE) -> United States of America | G11: =VLOOKUP(E11,country_continent!A:C,3,FALSE) -> North America | H11: Taft | I11: 3351 | J11: =IF(ISNUMBER(SEARCH("-", I11)), SUBSTITUTE(I11, "-", "/"), I11) -> 3351 | K11: 4812 | L11: =IF(ISNUMBER(SEARCH("-", K11)), SUBSTITUTE(K11, "-", "/"), K11) -> 4812 | M11: Regular | N11: Regular | O11: Regular | P11: 0 | Q11: OK | R11: M | S11: 1857 | T11: 1930 | Y11: https://urldefense.proofpoint.com/v2/url?u=http-3A__dbpedia.org_resource_William-5FHoward-5FTaft&d=BQID-g&c=kbmfwr1Yojg42sGEpaQh5ofMHBeTl9EI2eaqQZhHbOU&r=ZliGVSRwfirWoETOrKCh2RSnoygzVPWEk95Me9L-Kwo&m=EaKyFx9mpkhPdFxsxzvW_fiM3jbYwM3xYLjVbSFoDAg&s=bhEfrjiKenGUoUgvh3M4oCxkX9bJoHnDemF4c6OtEtE&e= | Z11: 0 | AA11: 1 | AB11: 0 | AC11: 0 | AF11: 1909 | AG11: 1913 | AO11: FALSE | AT11: 1461 | AU11: =ROUND(AT11/365,3) -> 4.003
A12: 10 | B12: USA-1913 | C12: 81dd2320-1e42-11e4-b4cd-db5882bf8def | D12: 2 | E12: USA | F12: =VLOOKUP(E12,country_continent!A:C,2,FALSE) -> United States of America | G12: =VLOOKUP(E12,country_continent!A:C,3,FALSE) -> North America | H12: Wilson | I12: 4812 | J12: =IF(ISNUMBER(SEARCH("-", I12)), SUBSTITUTE(I12, "-", "/"), I12) -> 4812 | K12: 7734 | L12: =IF(ISNUMBER(SEARCH("-", K12)), SUBSTITUTE(K12, "-", "/"), K12) -> 7734 | M12: Regular | N12: Regular | O12: Regular | P12: 0 | Q12: OK | R12: M | S12: 1856 | T12: 1924 | Y12: https://urldefense.proofpoint.com/v2/url?u=http-3A__dbpedia.org_resource_Woodrow-5FWilson&d=BQID-g&c=kbmfwr1Yojg42sGEpaQh5ofMHBeTl9EI2eaqQZhHbOU&r=ZliGVSRwfirWoETOrKCh2RSnoygzVPWEk95Me9L-Kwo&m=EaKyFx9mpkhPdFxsxzvW_fiM3jbYwM3xYLjVbSFoDAg&s=ClslkAGMxFPwxEqNwig9hoUm-6paj7k9nJQgfZTGBe0&e= | Z12: 0 | AA12: 1 | AB12: 0 | AC12: 0 | AF12: 1913 | AG12: 1921 | AO12: FALSE | AT12: 2922 | AU12: =ROUND(AT12/365,3) -> 8.005
A13: 11 | B13: USA-1921 | C13: 81dd2321-1e42-11e4-b4cd-db5882bf8def | D13: 2 | E13: USA | F13: =VLOOKUP(E13,country_continent!A:C,2,FALSE) -> United States of America | G13: =VLOOKUP(E13,country_continent!A:C,3,FALSE) -> North America | H13: Harding | I13: 7734 | J13: =IF(ISNUMBER(SEARCH("-", I13)), SUBSTITUTE(I13, "-", "/"), I13) -> 7734 | K13: 8616 | L13: =IF(ISNUMBER(SEARCH("-", K13)), SUBSTITUTE(K13, "-", "/"), K13) -> 8616 | M13: Regular | N13: Natural Death | O13: Regular | P13: 0 | Q13: Missing: Natural Death within Six Months of Losing Office | R13: M | S13: 1865 | T13: 1923 | Y13: https://urldefense.proofpoint.com/v2/url?u=http-3A__dbpedia.org_resource_Warren-5FG.-5FHarding&d=BQID-g&c=kbmfwr1Yojg42sGEpaQh5ofMHBeTl9EI2eaqQZhHbOU&r=ZliGVSRwfirWoETOrKCh2RSnoygzVPWEk95Me9L-Kwo&m=EaKyFx9mpkhPdFxsxzvW_fiM3jbYwM3xYLjVbSFoDAg&s=n19WCVJ00e6jAF9KgkqB1QA165ud9DQdOVE8YT4d3LE&e= | Z13: 0 | AA13: 2 | AB13: 0 | AC13: -777 | AF13: 1921 | AG13: 1923 | AO13: FALSE | AT13: 882 | AU13: =ROUND(AT13/365,3) -> 2.416
A14: 12 | B14: USA-1923 | C14: 81dd2322-1e42-11e4-b4cd-db5882bf8def | D14: 2 | E14: USA | F14: =VLOOKUP(E14,country_continent!A:C,2,FALSE) -> United States of America | G14: =VLOOKUP(E14,country_continent!A:C,3,FALSE) -> North America | H14: Coolidge | I14: 8616 | J14: =IF(ISNUMBER(SEARCH("-", I14)), SUBSTITUTE(I14, "-", "/"), I14) -> 8616 | K14: 10656 | L14: =IF(ISNUMBER(SEARCH("-", K14)), SUBSTITUTE(K14, "-", "/"), K14) -> 10656 | M14: Regular | N14: Regular | O14: Regular | P14: 0 | Q14: OK | R14: M | S14: 1872 | T14: 1933 | Y14: https://urldefense.proofpoint.com/v2/url?u=http-3A__dbpedia.org_resource_Calvin-5FCoolidge&d=BQID-g&c=kbmfwr1Yojg42sGEpaQh5ofMHBeTl9EI2eaqQZhHbOU&r=ZliGVSRwfirWoETOrKCh2RSnoygzVPWEk95Me9L-Kwo&m=EaKyFx9mpkhPdFxsxzvW_fiM3jbYwM3xYLjVbSFoDAg&s=NOK4weNtqbdh5IqnE0L5KCW3Toiiym3Zad3PQTU1A-8&e= | Z14: 0 | AA14: 1 | AB14: 0 | AC14: 0 | AF14: 1923 | AG14: 1929 | AO14: FALSE | AT14: 2040 | AU14: =ROUND(AT14/365,3) -> 5.589
A15: 13 | B15: USA-1929 | C15: 81dd53f2-1e42-11e4-b4cd-db5882bf8def | D15: 2 | E15: USA | F15: =VLOOKUP(E15,country_continent!A:C,2,FALSE) -> United States of America | G15: =VLOOKUP(E15,country_continent!A:C,3,FALSE) -> North America | H15: Hoover | I15: 10656 | J15: =IF(ISNUMBER(SEARCH("-", I15)), SUBSTITUTE(I15, "-", "/"), I15) -> 10656 | K15: 12117 | L15: =IF(ISNUMBER(SEARCH("-", K15)), SUBSTITUTE(K15, "-", "/"), K15) -> 12117 | M15: Regular | N15: Regular | O15: Regular | P15: 0 | Q15: OK | R15: M | S15: 1874 | T15: 1964 | Y15: https://urldefense.proofpoint.com/v2/url?u=http-3A__dbpedia.org_resource_Herbert-5FHoover&d=BQID-g&c=kbmfwr1Yojg42sGEpaQh5ofMHBeTl9EI2eaqQZhHbOU&r=ZliGVSRwfirWoETOrKCh2RSnoygzVPWEk95Me9L-Kwo&m=EaKyFx9mpkhPdFxsxzvW_fiM3jbYwM3xYLjVbSFoDAg&s=W0eBFvC2m3N346qhf_r9iGv5N_TNz7Zg6JxS7NQ5y7k&e= | Z15: 0 | AA15: 1 | AB15: 0 | AC15: 0 | AF15: 1929 | AG15: 1933 | AO15: FALSE | AT15: 1461 | AU15: =ROUND(AT15/365,3) -> 4.003
A16: 14 | B16: USA-1933 | C16: 81dd53f3-1e42-11e4-b4cd-db5882bf8def | D16: 2 | E16: USA | F16: =VLOOKUP(E16,country_continent!A:C,2,FALSE) -> United States of America | G16: =VLOOKUP(E16,country_continent!A:C,3,FALSE) -> North America | H16: Roosevelt, F. | I16: 12117 | J16: =IF(ISNUMBER(SEARCH("-", I16)), SUBSTITUTE(I16, "-", "/"), I16) -> 12117 | K16: 16539 | L16: =IF(ISNUMBER(SEARCH("-", K16)), SUBSTITUTE(K16, "-", "/"), K16) -> 16539 | M16: Regular | N16: Natural Death | O16: Regular | P16: 0 | Q16: Missing: Natural Death within Six Months of Losing Office | R16: M | S16: 1882 | T16: 1945 | Y16: https://urldefense.proofpoint.com/v2/url?u=http-3A__dbpedia.org_resource_Franklin-5FD.-5FRoosevelt&d=BQID-g&c=kbmfwr1Yojg42sGEpaQh5ofMHBeTl9EI2eaqQZhHbOU&r=ZliGVSRwfirWoETOrKCh2RSnoygzVPWEk95Me9L-Kwo&m=EaKyFx9mpkhPdFxsxzvW_fiM3jbYwM3xYLjVbSFoDAg&s=leTWvRisdM5Al2qrBj_GjPmFtyEZBnwk2iFJ1n4BAI8&e= | Z16: 0 | AA16: 2 | AB16: 0 | AC16: -777 | AD16: Nephew (distant) of Roosevelt, T.%81dd231e-1e42-11e4-b4cd-db5882bf8def | AE16: 1 | AF16: 1933 | AG16: 1945 | AO16: FALSE | AT16: 4422 | AU16: =ROUND(AT16/365,3) -> 12.115
A17: 15 | B17: USA-1945 | C17: 81dd53f4-1e42-11e4-b4cd-db5882bf8def | D17: 2 | E17: USA | F17: =VLOOKUP(E17,country_continent!A:C,2,FALSE) -> United States of America | G17: =VLOOKUP(E17,country_continent!A:C,3,FALSE) -> North America | H17: Truman | I17: 16539 | J17: =IF(ISNUMBER(SEARCH("-", I17)), SUBSTITUTE(I17, "-", "/"), I17) -> 16539 | K17: 19379 | L17: =IF(ISNUMBER(SEARCH("-", K17)), SUBSTITUTE(K17, "-", "/"), K17) -> 19379 | M17: Regular | N17: Regular | O17: Regular | P17: 0 | Q17: OK | R17: M | S17: 1884 | T17: 1972 | Y17: https://urldefense.proofpoint.com/v2/url?u=http-3A__dbpedia.org_resource_Harry-5FS.-5FTruman&d=BQID-g&c=kbmfwr1Yojg42sGEpaQh5ofMHBeTl9EI2eaqQZhHbOU&r=ZliGVSRwfirWoETOrKCh2RSnoygzVPWEk95Me9L-Kwo&m=EaKyFx9mpkhPdFxsxzvW_fiM3jbYwM3xYLjVbSFoDAg&s=8lvMz1dVajkRMhTCrwHn4rz8eECIgC0MEzNUFYGVA4s&e= | Z17: 0 | AA17: 1 | AB17: 0 | AC17: 0 | AF17: 1945 | AG17: 1953 | AN17: 9 | AO17: FALSE | AT17: 2840 | AU17: =ROUND(AT17/365,3) -> 7.781
A18: 16 | B18: USA-1953 | C18: 81dd53f5-1e42-11e4-b4cd-db5882bf8def | D18: 2 | E18: USA | F18: =VLOOKUP(E18,country_continent!A:C,2,FALSE) -> United States of America | G18: =VLOOKUP(E18,country_continent!A:C,3,FALSE) -> North America | H18: Eisenhower | I18: 19379 | J18: =IF(ISNUMBER(SEARCH("-", I18)), SUBSTITUTE(I18, "-", "/"), I18) -> 19379 | K18: 22301 | L18: =IF(ISNUMBER(SEARCH("-", K18)), SUBSTITUTE(K18, "-", "/"), K18) -> 22301 | M18: Regular | N18: Regular | O18: Regular | P18: 0 | Q18: OK | R18: M | S18: 1890 | T18: 1969 | Y18: https://urldefense.proofpoint.com/v2/url?u=http-3A__dbpedia.org_resource_Dwight-5FD.-5FEisenhower&d=BQID-g&c=kbmfwr1Yojg42sGEpaQh5ofMHBeTl9EI2eaqQZhHbOU&r=ZliGVSRwfirWoETOrKCh2RSnoygzVPWEk95Me9L-Kwo&m=EaKyFx9mpkhPdFxsxzvW_fiM3jbYwM3xYLjVbSFoDAg&s=rbOQoIR9XqJmFi2S0wTaEXDdPmKH7drhnWtGndAuYug&e= | Z18: 0 | AA18: 1 | AB18: 0 | AC18: 0 | AF18: 1953 | AG18: 1961 | AH18: 0.87910227 | AJ18: 1.1389667 | AK18: 29.8 | AL18: 1.65773 | AN18: 9 | AO18: FALSE | AT18: 2922 | AU18: =ROUND(AT18/365,3) -> 8.005
A19: 17 | B19: USA-1961 | C19: 81dd53f6-1e42-11e4-b4cd-db5882bf8def | D19: 2 | E19: USA | F19: =VLOOKUP(E19,country_continent!A:C,2,FALSE) -> United States of America | G19: =VLOOKUP(E19,country_continent!A:C,3,FALSE) -> North America | H19: Kennedy | I19: 22301 | J19: =IF(ISNUMBER(SEARCH("-", I19)), SUBSTITUTE(I19, "-", "/"), I19) -> 22301 | K19: 23337 | L19: =IF(ISNUMBER(SEARCH("-", K19)), SUBSTITUTE(K19, "-", "/"), K19) -> 23337 | M19: Regular | N19: Irregular | O19: Assassination by Unsupported Individual | P19: 0 | Q19: Death | R19: M | S19: 1917 | T19: 1963 | Y19: https://urldefense.proofpoint.com/v2/url?u=http-3A__dbpedia.org_resource_John-5FF.-5FKennedy&d=BQID-g&c=kbmfwr1Yojg42sGEpaQh5ofMHBeTl9EI2eaqQZhHbOU&r=ZliGVSRwfirWoETOrKCh2RSnoygzVPWEk95Me9L-Kwo&m=EaKyFx9mpkhPdFxsxzvW_fiM3jbYwM3xYLjVbSFoDAg&s=fz5b5YwDtYUHk4b8O09aRvlQy8YHM2GtYr6PPuqXASk&e= | Z19: 0 | AA19: 3 | AB19: 11 | AC19: 3 | AF19: 1961 | AG19: 1963 | AH19: 2.7517081 | AI19: 3345 | AJ19: 1.1896244 | AK19: 28.9 | AL19: 1.5449641 | AN19: 9 | AO19: FALSE | AT19: 1036 | AU19: =ROUND(AT19/365,3) -> 2.838
A20: 18 | B20: USA-1963 | C20: 81dd84c6-1e42-11e4-b4cd-db5882bf8def | D20: 2 | E20: USA | F20: =VLOOKUP(E20,country_continent!A:C,2,FALSE) -> United States of America | G20: =VLOOKUP(E20,country_continent!A:C,3,FALSE) -> North America | H20: Johnson | I20: 23337 | J20: =IF(ISNUMBER(SEARCH("-", I20)), SUBSTITUTE(I20, "-", "/"), I20) -> 23337 | K20: 25223 | L20: =IF(ISNUMBER(SEARCH("-", K20)), SUBSTITUTE(K20, "-", "/"), K20) -> 25223 | M20: Regular | N20: Regular | O20: Regular | P20: 0 | Q20: OK | R20: M | S20: 1908 | T20: 1973 | Y20: https://urldefense.proofpoint.com/v2/url?u=http-3A__dbpedia.org_resource_Lyndon-5FB.-5FJohnson&d=BQID-g&c=kbmfwr1Yojg42sGEpaQh5ofMHBeTl9EI2eaqQZhHbOU&r=ZliGVSRwfirWoETOrKCh2RSnoygzVPWEk95Me9L-Kwo&m=EaKyFx9mpkhPdFxsxzvW_fiM3jbYwM3xYLjVbSFoDAg&s=qMRnItod8XC9Z7Sa982pUDwLoBi4BVk8uy8zud2q9ho&e= | Z20: 0 | AA20: 1 | AB20: 0 | AC20: 0 | AF20: 1963 | AG20: 1969 | AH20: 3.6197824 | AI20: 4177.1429 | AJ20: 2.7594151 | AK20: 26.314286 | AL20: 1.1854087 | AN20: 8.57 | AO20: FALSE | AT20: 1886 | AU20: =ROUND(AT20/365,3) -> 5.167
A21: 19 | B21: USA-1969 | C21: 81dd84c7-1e42-11e4-b4cd-db5882bf8def | D21: 2 | E21: USA | F21: =VLOOKUP(E21,country_continent!A:C,2,FALSE) -> United States of America | G21: =VLOOKUP(E21,country_continent!A:C,3,FALSE) -> North America | H21: Nixon | I21: 25223 | J21: =IF(ISNUMBER(SEARCH("-", I21)), SUBSTITUTE(I21, "-", "/"), I21) -> 25223 | K21: 27250 | L21: =IF(ISNUMBER(SEARCH("-", K21)), SUBSTITUTE(K21, "-", "/"), K21) -> 27250 | M21: Regular | N21: Regular | O21: Regular | P21: 0 | Q21: OK | R21: M | S21: 1913 | T21: 1994 | Y21: https://urldefense.proofpoint.com/v2/url?u=http-3A__dbpedia.org_resource_Richard-5FNixon&d=BQID-g&c=kbmfwr1Yojg42sGEpaQh5ofMHBeTl9EI2eaqQZhHbOU&r=ZliGVSRwfirWoETOrKCh2RSnoygzVPWEk95Me9L-Kwo&m=EaKyFx9mpkhPdFxsxzvW_fiM3jbYwM3xYLjVbSFoDAg&s=Oup_2LmC4QJUy7zu8ke76SIe_xdKi4GnqB2hGVHCmBc&e= | Z21: 0 | AA21: 1 | AB21: 0 | AC21: 0 | AF21: 1969 | AG21: 1974 | AH21: 1.7450923 | AI21: 6276.6667 | AJ21: 5.6580824 | AK21: 21.916667 | AL21: 1.0575398 | AM21: 1.2481374 | AN21: 8.33 | AO21: FALSE | AT21: 2027 | AU21: =ROUND(AT21/365,3) -> 5.553
A22: 20 | B22: USA-1974 | C22: 81dd84c8-1e42-11e4-b4cd-db5882bf8def | D22: 2 | E22: USA | F22: =VLOOKUP(E22,country_continent!A:C,2,FALSE) -> United States of America | G22: =VLOOKUP(E22,country_continent!A:C,3,FALSE) -> North America | H22: Ford | I22: 27250 | J22: =IF(ISNUMBER(SEARCH("-", I22)), SUBSTITUTE(I22, "-", "/"), I22) -> 27250 | K22: 28145 | L22: =IF(ISNUMBER(SEARCH("-", K22)), SUBSTITUTE(K22, "-", "/"), K22) -> 28145 | M22: Regular | N22: Regular | O22: Regular | P22: 0 | Q22: OK | R22: M | S22: 1913 | T22: 2006 | Y22: https://urldefense.proofpoint.com/v2/url?u=http-3A__dbpedia.org_resource_Gerald-5FFord&d=BQID-g&c=kbmfwr1Yojg42sGEpaQh5ofMHBeTl9EI2eaqQZhHbOU&r=ZliGVSRwfirWoETOrKCh2RSnoygzVPWEk95Me9L-Kwo&m=EaKyFx9mpkhPdFxsxzvW_fiM3jbYwM3xYLjVbSFoDAg&s=rKHx6vASUC4iuo25L7XbRY9u7foC16KAVPOeee6VzWE&e= | Z22: 0 | AA22: 1 | AB22: 0 | AC22: 0 | AF22: 1974 | AG22: 1977 | AH22: 1.3346656 | AI22: 8835 | AJ22: 7.4945771 | AK22: 18.375 | AL22: 0.96390958 | AM22: 3.1777996 | AN22: 10 | AO22: FALSE | AT22: 895 | AU22: =ROUND(AT22/365,3) -> 2.452
A23: 21 | B23: USA-1977 | C23: 81dd84c9-1e42-11e4-b4cd-db5882bf8def | D23: 2 | E23: USA | F23: =VLOOKUP(E23,country_continent!A:C,2,FALSE) -> United States of America | G23: =VLOOKUP(E23,country_continent!A:C,3,FALSE) -> North America | H23: Carter | I23: 28145 | J23: =IF(ISNUMBER(SEARCH("-", I23)), SUBSTITUTE(I23, "-", "/"), I23) -> 28145 | K23: 29606 | L23: =IF(ISNUMBER(SEARCH("-", K23)), SUBSTITUTE(K23, "-", "/"), K23) -> 29606 | M23: Regular | N23: Regular | O23: Regular | P23: 0 | Q23: OK | R23: M | S23: 1924 | T23: -777 | Z23: 0 | AA23: 1 | AB23: 0 | AC23: 0 | AF23: 1977 | AG23: 1981 | AH23: 2.0721554 | AI23: 12216 | AJ23: 8.007851 | AK23: 15.68 | AL23: 1.0219854 | AM23: 4.1235118 | AN23: 10 | AO23: FALSE | AT23: 1461 | AU23: =ROUND(AT23/365,3) -> 4.003
A24: 22 | B24: USA-1981 | C24: 81dd84ca-1e42-11e4-b4cd-db5882bf8def | D24: 2 | E24: USA | F24: =VLOOKUP(E24,country_continent!A:C,2,FALSE) -> United States of America | G24: =VLOOKUP(E24,country_continent!A:C,3,FALSE) -> North America | H24: Reagan | I24: 29606 | J24: =IF(ISNUMBER(SEARCH("-", I24)), SUBSTITUTE(I24, "-", "/"), I24) -> 29606 | K24: 32528 | L24: =IF(ISNUMBER(SEARCH("-", K24)), SUBSTITUTE(K24, "-", "/"), K24) -> 32528 | M24: Regular | N24: Regular | O24: Regular | P24: 0 | Q24: OK | R24: M | S24: 1911 | T24: 2004 | Y24: https://urldefense.proofpoint.com/v2/url?u=http-3A__dbpedia.org_resource_Ronald-5FReagan&d=BQID-g&c=kbmfwr1Yojg42sGEpaQh5ofMHBeTl9EI2eaqQZhHbOU&r=ZliGVSRwfirWoETOrKCh2RSnoygzVPWEk95Me9L-Kwo&m=EaKyFx9mpkhPdFxsxzvW_fiM3jbYwM3xYLjVbSFoDAg&s=lkRsyOx2c3jHBdhtoz88j8z6MALbfv0cigW48DI3G54&e= | Z24: 0 | AA24: 1 | AB24: 0 | AC24: 0 | AF24: 1981 | AG24: 1989 | AH24: 2.5526741 | AI24: 18471.111 | AJ24: 4.2519358 | AK24: 12.822222 | AL24: 0.91905065 | AM24: 1.9675516 | AN24: 10 | AO24: FALSE | AT24: 2922 | AU24: =ROUND(AT24/365,3) -> 8.005
A25: 23 | B25: USA-1989 | C25: 81ddb59a-1e42-11e4-b4cd-db5882bf8def | D25: 2 | E25: USA | F25: =VLOOKUP(E25,country_continent!A:C,2,FALSE) -> United States of America | G25: =VLOOKUP(E25,country_continent!A:C,3,FALSE) -> North America | H25: G.H.W. Bush | I25: 32528 | J25: =IF(ISNUMBER(SEARCH("-", I25)), SUBSTITUTE(I25, "-", "/"), I25) -> 32528 | K25: 33989 | L25: =IF(ISNUMBER(SEARCH("-", K25)), SUBSTITUTE(K25, "-", "/"), K25) -> 33989 | M25: Regular | N25: Regular | O25: Regular | P25: 0 | Q25: OK | R25: M | S25: 1924 | T25: -777 | Z25: 0 | AA25: 1 | AB25: 0 | AC25: 0 | AD25: Father of G.W. Bush%81ddb59c-1e42-11e4-b4cd-db5882bf8def | AE25: 0 | AF25: 1989 | AG25: 1993 | AH25: 1.1014782 | AI25: 25258 | AJ25: 3.1390158 | AK25: 10.86 | AL25: 1.2231765 | AM25: 1.008135 | AN25: 10 | AO25: FALSE | AT25: 1461 | AU25: =ROUND(AT25/365,3) -> 4.003
A26: 24 | B26: USA-1993 | C26: 81ddb59b-1e42-11e4-b4cd-db5882bf8def | D26: 2 | E26: USA | F26: =VLOOKUP(E26,country_continent!A:C,2,FALSE) -> United States of America | G26: =VLOOKUP(E26,country_continent!A:C,3,FALSE) -> North America | H26: Clinton | I26: 33989 | J26: =IF(ISNUMBER(SEARCH("-", I26)), SUBSTITUTE(I26, "-", "/"), I26) -> 33989 | K26: 36911 | L26: =IF(ISNUMBER(SEARCH("-", K26)), SUBSTITUTE(K26, "-", "/"), K26) -> 36911 | M26: Regular | N26: Regular | O26: Regular | P26: 0 | Q26: OK | R26: M | S26: 1946 | T26: -777 | Y26: https://urldefense.proofpoint.com/v2/url?u=http-3A__dbpedia.org_resource_Bill-5FClinton&d=BQID-g&c=kbmfwr1Yojg42sGEpaQh5ofMHBeTl9EI2eaqQZhHbOU&r=ZliGVSRwfirWoETOrKCh2RSnoygzVPWEk95Me9L-Kwo&m=EaKyFx9mpkhPdFxsxzvW_fiM3jbYwM3xYLjVbSFoDAg&s=q83unszM5hbFxemh6q9IpkwHcXB177RSsz8TJwSDHMM&e= | Z26: 0 | AA26: 1 | AB26: 0 | AC26: 0 | AF26: 1993 | AG26: 2001 | AH26: 2.350748 | AI26: 31528.889 | AJ26: 1.9125859 | AK26: 9.0555556 | AL26: 1.1688556 | AM26: 0.83716593 | AN26: 10 | AO26: FALSE | AT26: 2922 | AU26: =ROUND(AT26/365,3) -> 8.005
A27: 25 | B27: USA-2001 | C27: 81ddb59c-1e42-11e4-b4cd-db5882bf8def | D27: 2 | E27: USA | F27: =VLOOKUP(E27,country_continent!A:C,2,FALSE) -> United States of America | G27: =VLOOKUP(E27,country_continent!A:C,3,FALSE) -> North America | H27: G.W. Bush | I27: 36912 | J27: =IF(ISNUMBER(SEARCH("-", I27)), SUBSTITUTE(I27, "-", "/"), I27) -> 36912 | K27: 39833 | L27: =IF(ISNUMBER(SEARCH("-", K27)), SUBSTITUTE(K27, "-", "/"), K27) -> 39833 | M27: Regular | N27: Regular | O27: Regular | P27: 0 | Q27: OK | R27: M | S27: 1946 | T27: -777 | Y27: https://urldefense.proofpoint.com/v2/url?u=http-3A__dbpedia.org_resource_George-5FW.-5FBush&d=BQID-g&c=kbmfwr1Yojg42sGEpaQh5ofMHBeTl9EI2eaqQZhHbOU&r=ZliGVSRwfirWoETOrKCh2RSnoygzVPWEk95Me9L-Kwo&m=EaKyFx9mpkhPdFxsxzvW_fiM3jbYwM3xYLjVbSFoDAg&s=yGi57JS_o8DCAgvCRWEExDmyN3b0n5O8GhHKvmXjJNI&e= | Z27: 0 | AA27: 1 | AB27: 0 | AC27: 0 | AD27: Son of G.H.W. Bush%81ddb59a-1e42-11e4-b4cd-db5882bf8def | AE27: 1 | AF27: 2001 | AG27: 2009 | AH27: 0.73827017 | AI27: 44054.444 | AJ27: 2.2156808 | AK27: 7.9333333 | AL27: 0.92911594 | AM27: 1.142556 | AN27: 10 | AO27: FALSE | AT27: 2921 | AU27: =ROUND(AT27/365,3) -> 8.003
A28: 26 | B28: USA-2009 | C28: 824fc72f-1e42-11e4-b4cd-db5882bf8def | D28: 2 | E28: USA | F28: =VLOOKUP(E28,country_continent!A:C,2,FALSE) -> United States of America | G28: =VLOOKUP(E28,country_continent!A:C,3,FALSE) -> North America | H28: Obama | I28: 39833 | J28: =IF(ISNUMBER(SEARCH("-", I28)), SUBSTITUTE(I28, "-", "/"), I28) -> 39833 | K28: 42369 | L28: =IF(ISNUMBER(SEARCH("-", K28)), SUBSTITUTE(K28, "-", "/"), K28) -> 42369 | M28: Regular | N28: Still in Office | O28: Still in Office | P28: 0 | Q28: Leader Still in Office | R28: M | S28: 1961 | T28: -777 | U28: 22497 | V28: 22497 | Z28: 0 | AA28: -888 | AB28: -888 | AC28: -888 | AF28: 2009 | AG28: 2015 | AH28: 0.83258764 | AI28: 52200 | AJ28: 1.4469833 | AK28: 7.0714286 | AL28: 0.80914957 | AM28: 0.77324406 | AN28: 10 | AO28: FALSE | AT28: 2536 | AU28: =ROUND(AT28/365,3) -> 6.948
A29: 27 | B29: CAN-1873 | C29: 81ddb59d-1e42-11e4-b4cd-db5882bf8def | D29: 20 | E29: CAN | F29: =VLOOKUP(E29,country_continent!A:C,2,FALSE) -> Canada | G29: =VLOOKUP(E29,country_continent!A:C,3,FALSE) -> North America | H29: Mackenzie | I29: 1873-11-07 | J29: =IF(ISNUMBER(SEARCH("-", I29)), SUBSTITUTE(I29, "-", "/"), I29) -> 1873/11/07 | K29: 1878-10-17 | L29: =IF(ISNUMBER(SEARCH("-", K29)), SUBSTITUTE(K29, "-", "/"), K29) -> 1878/10/17 | M29: Regular | N29: Regular | O29: Regular | P29: 0 | Q29: OK | R29: M | S29: 1822 | T29: 1892 | W29: 1892-04-17 | X29: 17apr1892 | Y29: https://urldefense.proofpoint.com/v2/url?u=http-3A__dbpedia.org_resource_Alexander-5FMackenzie&d=BQID-g&c=kbmfwr1Yojg42sGEpaQh5ofMHBeTl9EI2eaqQZhHbOU&r=ZliGVSRwfirWoETOrKCh2RSnoygzVPWEk95Me9L-Kwo&m=EaKyFx9mpkhPdFxsxzvW_fiM3jbYwM3xYLjVbSFoDAg&s=k6r3Pw-62MkbXzBATsAYVx1IuxSDqmIJjem1sBmmCwM&e= | Z29: 0 | AA29: 1 | AB29: 0 | AC29: 0 | AF29: 1873 | AG29: 1878 | AO29: TRUE | AP29: USA | AQ29: 1920 | AR29: 1959 | AS29: 39骞?1805 | AT29: 4.9418207 | AU29: =ROUND(AT29/365,3) -> 0.014
A30: 28 | B30: CAN-1878 | C30: 197110a8-3bbd-11e5-afeb-eb6f07f9fec7 | D30: 20 | E30: CAN | F30: =VLOOKUP(E30,country_continent!A:C,2,FALSE) -> Canada | G30: =VLOOKUP(E30,country_continent!A:C,3,FALSE) -> North America | H30: Macdonald | I30: 1878-10-17 | J30: =IF(ISNUMBER(SEARCH("-", I30)), SUBSTITUTE(I30, "-", "/"), I30) -> 1878/10/17 | K30: 1891-06-06 | L30: =IF(ISNUMBER(SEARCH("-", K30)), SUBSTITUTE(K30, "-", "/"), K30) -> 1891/06/06 | M30: Regular | N30: Natural Death | O30: Regular | P30: 1 | Q30: Missing: Natural Death within Six Months of Losing Office | R30: M | S30: 1815 | T30: 1891 | W30: 1891-06-06 | X30: 06jun1891 | Y30: https://urldefense.proofpoint.com/v2/url?u=http-3A__dbpedia.org_resource_John-5FA.-5FMacdonald&d=BQID-g&c=kbmfwr1Yojg42sGEpaQh5ofMHBeTl9EI2eaqQZhHbOU&r=ZliGVSRwfirWoETOrKCh2RSnoygzVPWEk95Me9L-Kwo&m=EaKyFx9mpkhPdFxsxzvW_fiM3jbYwM3xYLjVbSFoDAg&s=48mzgFtirP2HSdJCXb_rKfRzyhmk-xDMOoOtUE502mo&e= | Z30: 0 | AA30: 2 | AB30: 0 | AC30: -777 | AF30: 1878 | AG30: 1891 | AO30: TRUE | AP30: USA | AQ30: 1920 | AR30: 1959 | AS30: 39骞?4615 | AT30: 12.635181 | AU30: =ROUND(AT30/365,3) -> 0.035
A31: 29 | B31: CAN-1891 | C31: 81ddb59e-1e42-11e4-b4cd-db5882bf8def | D31: 20 | E31: CAN | F31: =VLOOKUP(E31,country_continent!A:C,2,FALSE) -> Canada | G31: =VLOOKUP(E31,country_continent!A:C,3,FALSE) -> North America | H31: Abbott | I31: 1891-06-16 | J31: =IF(ISNUMBER(SEARCH("-", I31)), SUBSTITUTE(I31, "-", "/"), I31) -> 1891/06/16 | K31: 1892-12-05 | L31: =IF(ISNUMBER(SEARCH("-", K31)), SUBSTITUTE(K31, "-", "/"), K31) -> 1892/12/05 | M31: Regular | N31: Regular | O31: Regular | P31: 0 | Q31: OK | R31: M | S31: 1821 | T31: 1893 | W31: 1893-10-30 | X31: 30oct1893 | Y31: https://urldefense.proofpoint.com/v2/url?u=http-3A__dbpedia.org_resource_John-5FAbbott&d=BQID-g&c=kbmfwr1Yojg42sGEpaQh5ofMHBeTl9EI2eaqQZhHbOU&r=ZliGVSRwfirWoETOrKCh2RSnoygzVPWEk95Me9L-Kwo&m=EaKyFx9mpkhPdFxsxzvW_fiM3jbYwM3xYLjVbSFoDAg&s=tUEQYgkxwyl5E0vwF5BABzdbSh2jlKuHVhC1SRmYCvw&e= | Z31: 0 | AA31: 1 | AB31: 0 | AC31: 0 | AF31: 1891 | AG31: 1892 | AO31: TRUE | AP31: USA | AQ31: 1920 | AR31: 1959 | AS31: 39骞?538 | AT31: 1.4729637 | AU31: =ROUND(AT31/365,3) -> 0.004
A32: 30 | B32: CAN-1892 | C32: 81dde678-1e42-11e4-b4cd-db5882bf8def | D32: 20 | E32: CAN | F32: =VLOOKUP(E32,country_continent!A:C,2,FALSE) -> Canada | G32: =VLOOKUP(E32,country_continent!A:C,3,FALSE) -> North America | H32: Thompson | I32: 1892-12-05 | J32: =IF(ISNUMBER(SEARCH("-", I32)), SUBSTITUTE(I32, "-", "/"), I32) -> 1892/12/05 | K32: 1894-12-12 | L32: =IF(ISNUMBER(SEARCH("-", K32)), SUBSTITUTE(K32, "-", "/"), K32) -> 1894/12/12 | M32: Regular | N32: Natural Death | O32: Regular | P32: 0 | Q32: Missing: Natural Death within Six Months of Losing Office | R32: M | S32: 1845 | T32: 1894 | Z32: 0 | AA32: 2 | AB32: 0 | AC32: -777 | AF32: 1892 | AG32: 1894 | AO32: TRUE | AP32: USA | AQ32: 1920 | AR32: 1959 | AS32: 39骞?737 | AT32: 2.017796 | AU32: =ROUND(AT32/365,3) -> 0.006
A33: 31 | B33: CAN-1894 | C33: 81dde679-1e42-11e4-b4cd-db5882bf8def | D33: 20 | E33: CAN | F33: =VLOOKUP(E33,country_continent!A:C,2,FALSE) -> Canada | G33: =VLOOKUP(E33,country_continent!A:C,3,FALSE) -> North America | H33: Bowell | I33: 1894-12-21 | J33: =IF(ISNUMBER(SEARCH("-", I33)), SUBSTITUTE(I33, "-", "/"), I33) -> 1894/12/21 | K33: 1896-05-01 | L33: =IF(ISNUMBER(SEARCH("-", K33)), SUBSTITUTE(K33, "-", "/"), K33) -> 1896/05/01 | M33: Regular | N33: Regular | O33: Regular | P33: 0 | Q33: OK | R33: M | S33: 1823 | T33: 1917 | Y33: https://urldefense.proofpoint.com/v2/url?u=http-3A__dbpedia.org_resource_Mackenzie-5FBowell&d=BQID-g&c=kbmfwr1Yojg42sGEpaQh5ofMHBeTl9EI2eaqQZhHbOU&r=ZliGVSRwfirWoETOrKCh2RSnoygzVPWEk95Me9L-Kwo&m=EaKyFx9mpkhPdFxsxzvW_fiM3jbYwM3xYLjVbSFoDAg&s=60PEb4noCXilyXVujuhdkkpnfQYWwm9wcV4KEfWb6jg&e= | Z33: 0 | AA33: 1 | AB33: 0 | AC33: 0 | AF33: 1894 | AG33: 1896 | AO33: TRUE | AP33: USA | AQ33: 1920 | AR33: 1959 | AS33: 39骞?497 | AT33: 1.3607118 | AU33: =ROUND(AT33/365,3) -> 0.004
A34: 32 | B34: CAN-1896-1 | C34: 81de174c-1e42-11e4-b4cd-db5882bf8def | D34: 20 | E34: CAN | F34: =VLOOKUP(E34,country_continent!A:C,2,FALSE) -> Canada | G34: =VLOOKUP(E34,country_continent!A:C,3,FALSE) -> North America | H34: Tupper | I34: 1896-05-01 | J34: =IF(ISNUMBER(SEARCH("-", I34)), SUBSTITUTE(I34, "-", "/"), I34) -> 1896/05/01 | K34: 1896-07-11 | L34: =IF(ISNUMBER(SEARCH("-", K34)), SUBSTITUTE(K34, "-", "/"), K34) -> 1896/07/11 | M34: Regular | N34: Regular | O34: Regular | P34: 0 | Q34: OK | R34: M | S34: 1821 | T34: 1915 | Y34: https://urldefense.proofpoint.com/v2/url?u=http-3A__dbpedia.org_resource_Charles-5FTupper&d=BQID-g&c=kbmfwr1Yojg42sGEpaQh5ofMHBeTl9EI2eaqQZhHbOU&r=ZliGVSRwfirWoETOrKCh2RSnoygzVPWEk95Me9L-Kwo&m=EaKyFx9mpkhPdFxsxzvW_fiM3jbYwM3xYLjVbSFoDAg&s=SwNSjv_Nr6aH1NoUFKWaj6wjrNADShiL7oApHYvsyRU&e= | Z34: 0 | AA34: 1 | AB34: 0 | AC34: 0 | AF34: 1896 | AG34: 1896 | AO34: TRUE | AP34: USA | AQ34: 1920 | AR34: 1959 | AS34: 39骞?71 | AT34: 0.19438741 | AU34: =ROUND(AT34/365,3) -> 0.001
A35: 33 | B35: CAN-1896-2 | C35: 81de4820-1e42-11e4-b4cd-db5882bf8def | D35: 20 | E35: CAN | F35: =VLOOKUP(E35,country_continent!A:C,2,FALSE) -> Canada | G35: =VLOOKUP(E35,country_continent!A:C,3,FALSE) -> North America | H35: Laurier | I35: 1896-07-11 | J35: =IF(ISNUMBER(SEARCH("-", I35)), SUBSTITUTE(I35, "-", "/"), I35) -> 1896/07/11 | K35: 4301 | L35: =IF(ISNUMBER(SEARCH("-", K35)), SUBSTITUTE(K35, "-", "/"), K35) -> 4301 | M35: Regular | N35: Regular | O35: Regular | P35: 0 | Q35: OK | R35: M | S35: 1841 | T35: 1919 | Y35: https://urldefense.proofpoint.com/v2/url?u=http-3A__dbpedia.org_resource_Wilfrid-5FLaurier&d=BQID-g&c=kbmfwr1Yojg42sGEpaQh5ofMHBeTl9EI2eaqQZhHbOU&r=ZliGVSRwfirWoETOrKCh2RSnoygzVPWEk95Me9L-Kwo&m=EaKyFx9mpkhPdFxsxzvW_fiM3jbYwM3xYLjVbSFoDAg&s=g09tst56QWN0KuNDYe_u8VrCyLuyc8gLksfx0KF9qDo&e= | Z35: 0 | AA35: 1 | AB35: 0 | AC35: 0 | AF35: 1896 | AG35: 1911 | AO35: TRUE | AP35: USA | AQ35: 1920 | AR35: 1959 | AS35: 39骞?5568 | AT35: 15.244353 | AU35: =ROUND(AT35/365,3) -> 0.042
A36: 34 | B36: CAN-1911 | C36: 81de4821-1e42-11e4-b4cd-db5882bf8def | D36: 20 | E36: CAN | F36: =VLOOKUP(E36,country_continent!A:C,2,FALSE) -> Canada | G36: =VLOOKUP(E36,country_continent!A:C,3,FALSE) -> North America | H36: Borden | I36: 4301 | J36: =IF(ISNUMBER(SEARCH("-", I36)), SUBSTITUTE(I36, "-", "/"), I36) -> 4301 | K36: 7467 | L36: =IF(ISNUMBER(SEARCH("-", K36)), SUBSTITUTE(K36, "-", "/"), K36) -> 7467 | M36: Regular | N36: Retired Due to Ill Health | O36: Regular | P36: 0 | Q36: OK | R36: M | S36: 1854 | T36: 1937 | Y36: https://urldefense.proofpoint.com/v2/url?u=http-3A__dbpedia.org_resource_Robert-5FBorden&d=BQID-g&c=kbmfwr1Yojg42sGEpaQh5ofMHBeTl9EI2eaqQZhHbOU&r=ZliGVSRwfirWoETOrKCh2RSnoygzVPWEk95Me9L-Kwo&m=EaKyFx9mpkhPdFxsxzvW_fiM3jbYwM3xYLjVbSFoDAg&s=3oDRQ0WFDLF-y9CZ9MpmZBulifIpPh6oUY9zPdR0D30&e= | Z36: 0 | AA36: 2.0999999 | AB36: 0 | AC36: 0 | AF36: 1911 | AG36: 1920 | AO36: TRUE | AP36: USA | AQ36: 1920 | AR36: 1959 | AS36: 39骞?3166 | AT36: 8.6680356 | AU36: =ROUND(AT36/365,3) -> 0.024
A37: 35 | B37: CAN-1920 | C37: 81de4822-1e42-11e4-b4cd-db5882bf8def | D37: 20 | E37: CAN | F37: =VLOOKUP(E37,country_continent!A:C,2,FALSE) -> Canada | G37: =VLOOKUP(E37,country_continent!A:C,3,FALSE) -> North America | H37: Meighen | I37: 7497 | J37: =IF(ISNUMBER(SEARCH("-", I37)), SUBSTITUTE(I37, "-", "/"), I37) -> 7497 | K37: 8034 | L37: =IF(ISNUMBER(SEARCH("-", K37)), SUBSTITUTE(K37, "-", "/"), K37) -> 8034 | M37: Regular | N37: Regular | O37: Regular | P37: 0 | Q37: OK | R37: M | S37: 1874 | T37: 1960 | Y37: https://urldefense.proofpoint.com/v2/url?u=http-3A__dbpedia.org_resource_Arthur-5FMeighen&d=BQID-g&c=kbmfwr1Yojg42sGEpaQh5ofMHBeTl9EI2eaqQZhHbOU&r=ZliGVSRwfirWoETOrKCh2RSnoygzVPWEk95Me9L-Kwo&m=EaKyFx9mpkhPdFxsxzvW_fiM3jbYwM3xYLjVbSFoDAg&s=beEjK11YQvAxkxJNw0MD71hEGdO1cPM93XBAjOSu95M&e= | Z37: 0 | AA37: 1 | AB37: 0 | AC37: 0 | AF37: 1920 | AG37: 1921 | AO37: TRUE | AP37: USA | AQ37: 1920 | AR37: 1959 | AS37: 39骞?537 | AT37: 1.4702259 | AU37: =ROUND(AT37/365,3) -> 0.004
A38: 36 | B38: CAN-1921 | C38: 81de4823-1e42-11e4-b4cd-db5882bf8def | D38: 20 | E38: CAN | F38: =VLOOKUP(E38,country_continent!A:C,2,FALSE) -> Canada | G38: =VLOOKUP(E38,country_continent!A:C,3,FALSE) -> North America | H38: King | I38: 8034 | J38: =IF(ISNUMBER(SEARCH("-", I38)), SUBSTITUTE(I38, "-", "/"), I38) -> 8034 | K38: 9676 | L38: =IF(ISNUMBER(SEARCH("-", K38)), SUBSTITUTE(K38, "-", "/"), K38) -> 9676 | M38: Regular | N38: Regular | O38: Regular | P38: 0 | Q38: OK | R38: M | S38: 1874 | T38: 1951 | Z38: 0 | AA38: 1 | AB38: 0 | AC38: 0 | AD38: Father of Ramon Baez%81e1556e-1e42-11e4-b4cd-db5882bf8def | AE38: 1 | AF38: 1921 | AG38: 1926 | AO38: TRUE | AP38: USA | AQ38: 1920 | AR38: 1959 | AS38: 39骞?1642 | AT38: 4.495551 | AU38: =ROUND(AT38/365,3) -> 0.012
A39: 37 | B39: CAN-1926-1 | C39: 81de4822-1e42-11e4-b4cd-db5882bf8def | D39: 20 | E39: CAN | F39: =VLOOKUP(E39,country_continent!A:C,2,FALSE) -> Canada | G39: =VLOOKUP(E39,country_continent!A:C,3,FALSE) -> North America | H39: Meighen | I39: 9677 | J39: =IF(ISNUMBER(SEARCH("-", I39)), SUBSTITUTE(I39, "-", "/"), I39) -> 9677 | K39: 9765 | L39: =IF(ISNUMBER(SEARCH("-", K39)), SUBSTITUTE(K39, "-", "/"), K39) -> 9765 | M39: Regular | N39: Regular | O39: Regular | P39: 1 | Q39: OK | R39: M | S39: 1874 | T39: 1960 | Y39: https://urldefense.proofpoint.com/v2/url?u=http-3A__dbpedia.org_resource_Arthur-5FMeighen&d=BQID-g&c=kbmfwr1Yojg42sGEpaQh5ofMHBeTl9EI2eaqQZhHbOU&r=ZliGVSRwfirWoETOrKCh2RSnoygzVPWEk95Me9L-Kwo&m=EaKyFx9mpkhPdFxsxzvW_fiM3jbYwM3xYLjVbSFoDAg&s=beEjK11YQvAxkxJNw0MD71hEGdO1cPM93XBAjOSu95M&e= | Z39: 0 | AA39: 1 | AB39: 0 | AC39: 0 | AF39: 1926 | AG39: 1926 | AO39: TRUE | AP39: USA | AQ39: 1920 | AR39: 1959 | AS39: 39骞?88 | AT39: 0.24093087 | AU39: =ROUND(AT39/365,3) -> 0.001
A40: 38 | B40: CAN-1926-2 | C40: 81de4823-1e42-11e4-b4cd-db5882bf8def | D40: 20 | E40: CAN | F40: =VLOOKUP(E40,country_continent!A:C,2,FALSE) -> Canada | G40: =VLOOKUP(E40,country_continent!A:C,3,FALSE) -> North America | H40: King | I40: 9765 | J40: =IF(ISNUMBER(SEARCH("-", I40)), SUBSTITUTE(I40, "-", "/"), I40) -> 9765 | K40: 11177 | L40: =IF(ISNUMBER(SEARCH("-", K40)), SUBSTITUTE(K40, "-", "/"), K40) -> 11177 | M40: Regular | N40: Regular | O40: Regular | P40: 1 | Q40: OK | R40: M | S40: 1874 | T40: 1951 | Z40: 0 | AA40: 1 | AB40: 0 | AC40: 0 | AD40: Father of Ramon Baez%81e1556e-1e42-11e4-b4cd-db5882bf8def | AE40: 1 | AF40: 1926 | AG40: 1930 | AO40: TRUE | AP40: USA | AQ40: 1920 | AR40: 1959 | AS40: 39骞?1412 | AT40: 3.8658453 | AU40: =ROUND(AT40/365,3) -> 0.011
A41: 39 | B41: CAN-1930 | C41: 81de4824-1e42-11e4-b4cd-db5882bf8def | D41: 20 | E41: CAN | F41: =VLOOKUP(E41,country_continent!A:C,2,FALSE) -> Canada | G41: =VLOOKUP(E41,country_continent!A:C,3,FALSE) -> North America | H41: Bennett | I41: 11177 | J41: =IF(ISNUMBER(SEARCH("-", I41)), SUBSTITUTE(I41, "-", "/"), I41) -> 11177 | K41: 13080 | L41: =IF(ISNUMBER(SEARCH("-", K41)), SUBSTITUTE(K41, "-", "/"), K41) -> 13080 | M41: Regular | N41: Regular | O41: Regular | P41: 0 | Q41: OK | R41: M | S41: 1870 | T41: 1947 | Y41: https://urldefense.proofpoint.com/v2/url?u=http-3A__dbpedia.org_resource_R.-5FB.-5FBennett&d=BQID-g&c=kbmfwr1Yojg42sGEpaQh5ofMHBeTl9EI2eaqQZhHbOU&r=ZliGVSRwfirWoETOrKCh2RSnoygzVPWEk95Me9L-Kwo&m=EaKyFx9mpkhPdFxsxzvW_fiM3jbYwM3xYLjVbSFoDAg&s=N7o5FG1J5XmgggL0nAT5JmcCC4EUqYULZEvFd0z-RGk&e= | Z41: 0 | AA41: 1 | AB41: 0 | AC41: 0 | AF41: 1930 | AG41: 1935 | AO41: TRUE | AP41: USA | AQ41: 1920 | AR41: 1959 | AS41: 39骞?1903 | AT41: 5.21013 | AU41: =ROUND(AT41/365,3) -> 0.014
A42: 40 | B42: CAN-1935 | C42: 81de4823-1e42-11e4-b4cd-db5882bf8def | D42: 20 | E42: CAN | F42: =VLOOKUP(E42,country_continent!A:C,2,FALSE) -> Canada | G42: =VLOOKUP(E42,country_continent!A:C,3,FALSE) -> North America | H42: King | I42: 13080 | J42: =IF(ISNUMBER(SEARCH("-", I42)), SUBSTITUTE(I42, "-", "/"), I42) -> 13080 | K42: 17852 | L42: =IF(ISNUMBER(SEARCH("-", K42)), SUBSTITUTE(K42, "-", "/"), K42) -> 17852 | M42: Regular | N42: Retired Due to Ill Health | O42: Regular | P42: 2 | Q42: OK | R42: M | S42: 1874 | T42: 1951 | Z42: 0 | AA42: 2.0999999 | AB42: 0 | AC42: 0 | AD42: Father of Ramon Baez%81e1556e-1e42-11e4-b4cd-db5882bf8def | AE42: 1 | AF42: 1935 | AG42: 1948 | AN42: 10 | AO42: TRUE | AP42: USA | AQ42: 1920 | AR42: 1959 | AS42: 39骞?4772 | AT42: 13.065024 | AU42: =ROUND(AT42/365,3) -> 0.036
A43: 41 | B43: CAN-1948 | C43: 81de78f4-1e42-11e4-b4cd-db5882bf8def | D43: 20 | E43: CAN | F43: =VLOOKUP(E43,country_continent!A:C,2,FALSE) -> Canada | G43: =VLOOKUP(E43,country_continent!A:C,3,FALSE) -> North America | H43: St. Laurent | I43: 17852 | J43: =IF(ISNUMBER(SEARCH("-", I43)), SUBSTITUTE(I43, "-", "/"), I43) -> 17852 | K43: 20992 | L43: =IF(ISNUMBER(SEARCH("-", K43)), SUBSTITUTE(K43, "-", "/"), K43) -> 20992 | M43: Regular | N43: Regular | O43: Regular | P43: 0 | Q43: OK | R43: M | S43: 1882 | T43: 1973 | U43: 1882-02-01 | V43: 01feb1882 | Y43: https://urldefense.proofpoint.com/v2/url?u=http-3A__dbpedia.org_resource_Louis-5FSt.-5FLaurent&d=BQID-g&c=kbmfwr1Yojg42sGEpaQh5ofMHBeTl9EI2eaqQZhHbOU&r=ZliGVSRwfirWoETOrKCh2RSnoygzVPWEk95Me9L-Kwo&m=EaKyFx9mpkhPdFxsxzvW_fiM3jbYwM3xYLjVbSFoDAg&s=1_JqIUI-cEV1iwLTvxoeZp0dBayilsdlMLGZCNNJUFg&e= | Z43: 0 | AA43: 1 | AB43: 0 | AC43: 0 | AF43: 1948 | AG43: 1957 | AN43: 10 | AO43: TRUE | AP43: USA | AQ43: 1920 | AR43: 1959 | AS43: 39骞?3140 | AT43: 8.5968515 | AU43: =ROUND(AT43/365,3) -> 0.024
A44: 42 | B44: CAN-1957 | C44: 81de78f5-1e42-11e4-b4cd-db5882bf8def | D44: 20 | E44: CAN | F44: =VLOOKUP(E44,country_continent!A:C,2,FALSE) -> Canada | G44: =VLOOKUP(E44,country_continent!A:C,3,FALSE) -> North America | H44: Diefenbaker | I44: 20992 | J44: =IF(ISNUMBER(SEARCH("-", I44)), SUBSTITUTE(I44, "-", "/"), I44) -> 20992 | K44: 23123 | L44: =IF(ISNUMBER(SEARCH("-", K44)), SUBSTITUTE(K44, "-", "/"), K44) -> 23123 | M44: Regular | N44: Regular | O44: Regular | P44: 0 | Q44: OK | R44: M | S44: 1895 | T44: 1979 | U44: 1895-09-18 | V44: 18sep1895 | Y44: https://urldefense.proofpoint.com/v2/url?u=http-3A__dbpedia.org_resource_John-5FDiefenbaker&d=BQID-g&c=kbmfwr1Yojg42sGEpaQh5ofMHBeTl9EI2eaqQZhHbOU&r=ZliGVSRwfirWoETOrKCh2RSnoygzVPWEk95Me9L-Kwo&m=EaKyFx9mpkhPdFxsxzvW_fiM3jbYwM3xYLjVbSFoDAg&s=6TYAB7L7Ufes-gYVer7NsjNfu7pTB-NX3P5lsZ8wF7M&e= | Z44: 0 | AA44: 1 | AB44: 0 | AC44: 0 | AF44: 1957 | AG44: 1963 | AH44: 3.3078933 | AI44: 2395 | AJ44: 1.9788427 | AK44: 31 | AL44: 1.9073062 | AN44: 10 | AO44: TRUE | AP44: USA | AQ44: 1920 | AR44: 1959 | AS44: 39骞?2131 | AT44: 5.83436 | AU44: =ROUND(AT44/365,3) -> 0.016
A45: 43 | B45: CAN-1963 | C45: 81de78f6-1e42-11e4-b4cd-db5882bf8def | D45: 20 | E45: CAN | F45: =VLOOKUP(E45,country_continent!A:C,2,FALSE) -> Canada | G45: =VLOOKUP(E45,country_continent!A:C,3,FALSE) -> North America | H45: Pearson | I45: 23123 | J45: =IF(ISNUMBER(SEARCH("-", I45)), SUBSTITUTE(I45, "-", "/"), I45) -> 23123 | K45: 24948 | L45: =IF(ISNUMBER(SEARCH("-", K45)), SUBSTITUTE(K45, "-", "/"), K45) -> 24948 | M45: Regular | N45: Regular | O45: Regular | P45: 0 | Q45: OK | R45: M | S45: 1897 | T45: 1972 | U45: 1897-04-23 | V45: 23apr1897 | Y45: https://urldefense.proofpoint.com/v2/url?u=http-3A__dbpedia.org_resource_Lester-5FB.-5FPearson&d=BQID-g&c=kbmfwr1Yojg42sGEpaQh5ofMHBeTl9EI2eaqQZhHbOU&r=ZliGVSRwfirWoETOrKCh2RSnoygzVPWEk95Me9L-Kwo&m=EaKyFx9mpkhPdFxsxzvW_fiM3jbYwM3xYLjVbSFoDAg&s=cweceAKDcxiJMyb-uwPUGfcmPYzaVQGdRXRqVDiZmJM&e= | Z45: 0 | AA45: 1 | AB45: 0 | AC45: 0 | AF45: 1963 | AG45: 1968 | AH45: 3.6286986 | AI45: 2868.3333 | AJ45: 3.7048759 | AK45: 26.616667 | AL45: 1.8057177 | AN45: 10 | AO45: TRUE | AP45: USA | AQ45: 1920 | AR45: 1959 | AS45: 39骞?1825 | AT45: 4.9965777 | AU45: =ROUND(AT45/365,3) -> 0.014
A46: 44 | B46: CAN-1968 | C46: 81de78f7-1e42-11e4-b4cd-db5882bf8def | D46: 20 | E46: CAN | F46: =VLOOKUP(E46,country_continent!A:C,2,FALSE) -> Canada | G46: =VLOOKUP(E46,country_continent!A:C,3,FALSE) -> North America | H46: Pierre Trudeau | I46: 24948 | J46: =IF(ISNUMBER(SEARCH("-", I46)), SUBSTITUTE(I46, "-", "/"), I46) -> 24948 | K46: 29010 | L46: =IF(ISNUMBER(SEARCH("-", K46)), SUBSTITUTE(K46, "-", "/"), K46) -> 29010 | M46: Regular | N46: Regular | O46: Regular | P46: 0 | Q46: OK | R46: M | S46: 1919 | T46: 2000 | U46: 7231 | V46: 7231 | Y46: https://urldefense.proofpoint.com/v2/url?u=http-3A__dbpedia.org_resource_Pierre-5FTrudeau&d=BQID-g&c=kbmfwr1Yojg42sGEpaQh5ofMHBeTl9EI2eaqQZhHbOU&r=ZliGVSRwfirWoETOrKCh2RSnoygzVPWEk95Me9L-Kwo&m=EaKyFx9mpkhPdFxsxzvW_fiM3jbYwM3xYLjVbSFoDAg&s=w4_-YXRnusU30RhiSPp87RPt4ZI3h33z8sN7421A2Kw&e= | Z46: 0 | AA46: 1 | AB46: 0 | AC46: 0 | AD46: Father of Justin Trudeau%43f5ae9c-de6a-11e5-ba44-bb6d7c1a9a58 | AE46: 0 | AF46: 1968 | AG46: 1979 | AH46: 2.7869032 | AI46: 6671.6667 | AJ46: 7.7720869 | AK46: 18.508333 | AL46: 1.4191122 | AM46: 3.9622296 | AN46: 10 | AO46: TRUE | AP46: USA | AQ46: 1920 | AR46: 1959 | AS46: 39骞?4062 | AT46: 11.12115 | AU46: =ROUND(AT46/365,3) -> 0.03
A47: 45 | B47: CAN-1979 | C47: 81de78f8-1e42-11e4-b4cd-db5882bf8def | D47: 20 | E47: CAN | F47: =VLOOKUP(E47,country_continent!A:C,2,FALSE) -> Canada | G47: =VLOOKUP(E47,country_continent!A:C,3,FALSE) -> North America | H47: Clark | I47: 29010 | J47: =IF(ISNUMBER(SEARCH("-", I47)), SUBSTITUTE(I47, "-", "/"), I47) -> 29010 | K47: 29283 | L47: =IF(ISNUMBER(SEARCH("-", K47)), SUBSTITUTE(K47, "-", "/"), K47) -> 29283 | M47: Regular | N47: Regular | O47: Regular | P47: 0 | Q47: OK | R47: M | S47: 1939 | T47: -777 | U47: 14401 | V47: 14401 | Y47: https://urldefense.proofpoint.com/v2/url?u=http-3A__dbpedia.org_resource_Joe-5FClark&d=BQID-g&c=kbmfwr1Yojg42sGEpaQh5ofMHBeTl9EI2eaqQZhHbOU&r=ZliGVSRwfirWoETOrKCh2RSnoygzVPWEk95Me9L-Kwo&m=EaKyFx9mpkhPdFxsxzvW_fiM3jbYwM3xYLjVbSFoDAg&s=-HfjxvUln5ECr1JP_5QDje-BndEcDO-E7JKce9IdRO8&e= | Z47: 0 | AA47: 1 | AB47: 0 | AC47: 0 | AF47: 1979 | AG47: 1980 | AH47: 1.7858414 | AI47: 11100 | AJ47: 10.06297 | AK47: 12.9 | AL47: 1.1396469 | AM47: 8.754096 | AN47: 10 | AO47: TRUE | AP47: USA | AQ47: 1920 | AR47: 1959 | AS47: 39骞?273 | AT47: 0.74743326 | AU47: =ROUND(AT47/365,3) -> 0.002
A48: 46 | B48: CAN-1980 | C48: 81de78f7-1e42-11e4-b4cd-db5882bf8def | D48: 20 | E48: CAN | F48: =VLOOKUP(E48,country_continent!A:C,2,FALSE) -> Canada | G48: =VLOOKUP(E48,country_continent!A:C,3,FALSE) -> North America | H48: Pierre Trudeau | I48: 29283 | J48: =IF(ISNUMBER(SEARCH("-", I48)), SUBSTITUTE(I48, "-", "/"), I48) -> 29283 | K48: 30863 | L48: =IF(ISNUMBER(SEARCH("-", K48)), SUBSTITUTE(K48, "-", "/"), K48) -> 30863 | M48: Regular | N48: Regular | O48: Regular | P48: 1 | Q48: OK | R48: M | S48: 1919 | T48: 2000 | U48: 7231 | V48: 7231 | Y48: https://urldefense.proofpoint.com/v2/url?u=http-3A__dbpedia.org_resource_Pierre-5FTrudeau&d=BQID-g&c=kbmfwr1Yojg42sGEpaQh5ofMHBeTl9EI2eaqQZhHbOU&r=ZliGVSRwfirWoETOrKCh2RSnoygzVPWEk95Me9L-Kwo&m=EaKyFx9mpkhPdFxsxzvW_fiM3jbYwM3xYLjVbSFoDAg&s=w4_-YXRnusU30RhiSPp87RPt4ZI3h33z8sN7421A2Kw&e= | Z48: 0 | AA48: 1 | AB48: 0 | AC48: 0 | AD48: Father of Justin Trudeau%43f5ae9c-de6a-11e5-ba44-bb6d7c1a9a58 | AE48: 0 | AF48: 1980 | AG48: 1984 | AH48: 1.032214 | AI48: 12240 | AJ48: 7.8247582 | AK48: 11.24 | AL48: 1.1290278 | AM48: 5.3364944 | AN48: 10 | AO48: TRUE | AP48: USA | AQ48: 1920 | AR48: 1959 | AS48: 39骞?1580 | AT48: 4.3258042 | AU48: =ROUND(AT48/365,3) -> 0.012
A49: 47 | B49: CAN-1984-1 | C49: 81de78f9-1e42-11e4-b4cd-db5882bf8def | D49: 20 | E49: CAN | F49: =VLOOKUP(E49,country_continent!A:C,2,FALSE) -> Canada | G49: =VLOOKUP(E49,country_continent!A:C,3,FALSE) -> North America | H49: Turner | I49: 30863 | J49: =IF(ISNUMBER(SEARCH("-", I49)), SUBSTITUTE(I49, "-", "/"), I49) -> 30863 | K49: 30942 | L49: =IF(ISNUMBER(SEARCH("-", K49)), SUBSTITUTE(K49, "-", "/"), K49) -> 30942 | M49: Regular | N49: Regular | O49: Regular | P49: 0 | Q49: OK | R49: M | S49: 1929 | T49: -777 | U49: 10751 | V49: 10751 | Y49: https://urldefense.proofpoint.com/v2/url?u=http-3A__dbpedia.org_resource_John-5FTurner&d=BQID-g&c=kbmfwr1Yojg42sGEpaQh5ofMHBeTl9EI2eaqQZhHbOU&r=ZliGVSRwfirWoETOrKCh2RSnoygzVPWEk95Me9L-Kwo&m=EaKyFx9mpkhPdFxsxzvW_fiM3jbYwM3xYLjVbSFoDAg&s=2LjzF2jtH7HeWMa4ikmSHUzgIyteqWSam74Ug2FhHlY&e= | Z49: 0 | AA49: 1 | AB49: 0 | AC49: 0 | AF49: 1984 | AG49: 1984 | AH49: 4.9035542 | AI49: 13150 | AJ49: 3.5453903 | AK49: 10.1 | AL49: 0.94403472 | AM49: 4.2771565 | AN49: 10 | AO49: TRUE | AP49: USA | AQ49: 1920 | AR49: 1959 | AS49: 39骞?79 | AT49: 0.21629021 | AU49: =ROUND(AT49/365,3) -> 0.001
A50: 48 | B50: CAN-1984-2 | C50: 81dea9c8-1e42-11e4-b4cd-db5882bf8def | D50: 20 | E50: CAN | F50: =VLOOKUP(E50,country_continent!A:C,2,FALSE) -> Canada | G50: =VLOOKUP(E50,country_continent!A:C,3,FALSE) -> North America | H50: Mulroney | I50: 30942 | J50: =IF(ISNUMBER(SEARCH("-", I50)), SUBSTITUTE(I50, "-", "/"), I50) -> 30942 | K50: 34145 | L50: =IF(ISNUMBER(SEARCH("-", K50)), SUBSTITUTE(K50, "-", "/"), K50) -> 34145 | M50: Regular | N50: Regular | O50: Regular | P50: 0 | Q50: OK | R50: M | S50: 1939 | T50: -777 | U50: 14324 | V50: 14324 | Y50: https://urldefense.proofpoint.com/v2/url?u=http-3A__dbpedia.org_resource_Brian-5FMulroney&d=BQID-g&c=kbmfwr1Yojg42sGEpaQh5ofMHBeTl9EI2eaqQZhHbOU&r=ZliGVSRwfirWoETOrKCh2RSnoygzVPWEk95Me9L-Kwo&m=EaKyFx9mpkhPdFxsxzvW_fiM3jbYwM3xYLjVbSFoDAg&s=ISn4dFD4sYHvrdfqixCO51zXVodWbv_BhjldzdQAYeI&e= | Z50: 0 | AA50: 1 | AB50: 0 | AC50: 0 | AF50: 1984 | AG50: 1993 | AH50: 1.2734713 | AI50: 18078 | AJ50: 3.3197977 | AK50: 8.7 | AL50: 1.2293864 | AM50: 2.8268863 | AN50: 10 | AO50: TRUE | AP50: USA | AQ50: 1920 | AR50: 1959 | AS50: 39骞?3203 | AT50: 8.7693361 | AU50: =ROUND(AT50/365,3) -> 0.024
A51: 49 | B51: CAN-1993-1 | C51: 81dea9c9-1e42-11e4-b4cd-db5882bf8def | D51: 20 | E51: CAN | F51: =VLOOKUP(E51,country_continent!A:C,2,FALSE) -> Canada | G51: =VLOOKUP(E51,country_continent!A:C,3,FALSE) -> North America | H51: Kim Campbell | I51: 34145 | J51: =IF(ISNUMBER(SEARCH("-", I51)), SUBSTITUTE(I51, "-", "/"), I51) -> 34145 | K51: 34277 | L51: =IF(ISNUMBER(SEARCH("-", K51)), SUBSTITUTE(K51, "-", "/"), K51) -> 34277 | M51: Regular | N51: Regular | O51: Regular | P51: 0 | Q51: OK | R51: F | S51: 1947 | T51: -777 | Z51: 0 | AA51: 1 | AB51: 0 | AC51: 0 | AF51: 1993 | AG51: 1993 | AH51: 1.5357458 | AI51: 21270 | AJ51: 1.2890429 | AK51: 7.4 | AL51: 1.0989309 | AM51: 2.618825 | AN51: 10 | AO51: TRUE | AP51: USA | AQ51: 1920 | AR51: 1959 | AS51: 39骞?132 | AT51: 0.3613963 | AU51: =ROUND(AT51/365,3) -> 0.001
A52: 50 | B52: CAN-1993-2 | C52: 81dea9ca-1e42-11e4-b4cd-db5882bf8def | D52: 20 | E52: CAN | F52: =VLOOKUP(E52,country_continent!A:C,2,FALSE) -> Canada | G52: =VLOOKUP(E52,country_continent!A:C,3,FALSE) -> North America | H52: Chretien | I52: 34277 | J52: =IF(ISNUMBER(SEARCH("-", I52)), SUBSTITUTE(I52, "-", "/"), I52) -> 34277 | K52: 37967 | L52: =IF(ISNUMBER(SEARCH("-", K52)), SUBSTITUTE(K52, "-", "/"), K52) -> 37967 | M52: Regular | N52: Regular | O52: Regular | P52: 0 | Q52: OK | R52: M | S52: 1939 | T52: -777 | Z52: 0 | AA52: 1 | AB52: 0 | AC52: 0 | AF52: 1993 | AG52: 2003 | AH52: 2.3129884 | AI52: 22040 | AJ52: 1.8209245 | AK52: 6.5636364 | AL52: 0.99202836 | AM52: 2.9697651 | AN52: 10 | AO52: TRUE | AP52: USA | AQ52: 1920 | AR52: 1959 | AS52: 39骞?3690 | AT52: 10.102669 | AU52: =ROUND(AT52/365,3) -> 0.028
A53: 51 | B53: CAN-2003 | C53: 81dea9cb-1e42-11e4-b4cd-db5882bf8def | D53: 20 | E53: CAN | F53: =VLOOKUP(E53,country_continent!A:C,2,FALSE) -> Canada | G53: =VLOOKUP(E53,country_continent!A:C,3,FALSE) -> North America | H53: Paul Martin | I53: 37967 | J53: =IF(ISNUMBER(SEARCH("-", I53)), SUBSTITUTE(I53, "-", "/"), I53) -> 37967 | K53: 38754 | L53: =IF(ISNUMBER(SEARCH("-", K53)), SUBSTITUTE(K53, "-", "/"), K53) -> 38754 | M53: Regular | N53: Regular | O53: Regular | P53: 0 | Q53: OK | R53: M | S53: 1938 | T53: -777 | Z53: 0 | AA53: 1 | AB53: 0 | AC53: 0 | AF53: 2003 | AG53: 2006 | AH53: 1.7178281 | AI53: 31805 | AJ53: 3.0493555 | AK53: 6.1 | AL53: 0.94801486 | AM53: 4.5540227 | AN53: 10 | AO53: TRUE | AP53: USA | AQ53: 1920 | AR53: 1959 | AS53: 39骞?787 | AT53: 2.1546886 | AU53: =ROUND(AT53/365,3) -> 0.006
A54: 52 | B54: CAN-2006 | C54: 824ff7fe-1e42-11e4-b4cd-db5882bf8def | D54: 20 | E54: CAN | F54: =VLOOKUP(E54,country_continent!A:C,2,FALSE) -> Canada | G54: =VLOOKUP(E54,country_continent!A:C,3,FALSE) -> North America | H54: Harper | I54: 38754 | J54: =IF(ISNUMBER(SEARCH("-", I54)), SUBSTITUTE(I54, "-", "/"), I54) -> 38754 | K54: 42312 | L54: =IF(ISNUMBER(SEARCH("-", K54)), SUBSTITUTE(K54, "-", "/"), K54) -> 42312 | M54: Regular | N54: Regular | O54: Regular | P54: 0 | Q54: Missing: Left Office after 2014-12-31 | R54: M | S54: 1959 | T54: -777 | U54: 21670 | V54: 21670 | Z54: 0 | AA54: 1 | AB54: 0 | AC54: -999 | AF54: 2006 | AG54: 2015 | AH54: 0.62896125 | AI54: 46294 | AJ54: 1.7667935 | AK54: 5.69 | AL54: 1.0198402 | AM54: 2.488046 | AN54: 10 | AO54: TRUE | AP54: USA | AQ54: 1920 | AR54: 1959 | AS54: 39骞?3558 | AT54: 9.7412731 | AU54: =ROUND(AT54/365,3) -> 0.027
A55: 53 | B55: CAN-2015 | C55: 43f5ae9c-de6a-11e5-ba44-bb6d7c1a9a58 | D55: 20 | E55: CAN | F55: =VLOOKUP(E55,country_continent!A:C,2,FALSE) -> Canada | G55: =VLOOKUP(E55,country_continent!A:C,3,FALSE) -> North America | H55: Justin Trudeau | I55: 42312 | J55: =IF(ISNUMBER(SEARCH("-", I55)), SUBSTITUTE(I55, "-", "/"), I55) -> 42312 | K55: 42369 | L55: =IF(ISNUMBER(SEARCH("-", K55)), SUBSTITUTE(K55, "-", "/"), K55) -> 42369 | M55: Regular | N55: Still in Office | O55: Still in Office | P55: 0 | Q55: Missing: Left Office after 2014-12-31 | R55: M | S55: 1971 | T55: -777 | U55: 26292 | V55: 26292 | Z55: 0 | AA55: -888 | AB55: 0 | AC55: -999 | AD55: Son of Pierre Trudeau%81de78f7-1e42-11e4-b4cd-db5882bf8def | AE55: 1 | AF55: 2015 | AG55: 2015 | AH55: -0.11236916 | AI55: 47580 | AJ55: -0.86765132 | AK55: 5.4 | AL55: 0.76030015 | AM55: 0.33293384 | AN55: 10 | AO55: TRUE | AP55: USA | AQ55: 1920 | AR55: 1959 | AS55: 39骞?57 | AT55: 0.15605749 | AU55: =ROUND(AT55/365,3) -> 0
A56: 54 | B56: BHM-1967 | C56: 81dea9cc-1e42-11e4-b4cd-db5882bf8def | D56: 31 | E56: BHM | F56: =VLOOKUP(E56,country_continent!A:C,2,FALSE) -> The Bahamas | G56: =VLOOKUP(E56,country_continent!A:C,3,FALSE) -> North America | H56: Pindling | I56: 24488 | J56: =IF(ISNUMBER(SEARCH("-", I56)), SUBSTITUTE(I56, "-", "/"), I56) -> 24488 | K56: 33837 | L56: =IF(ISNUMBER(SEARCH("-", K56)), SUBSTITUTE(K56, "-", "/"), K56) -> 33837 | M56: Regular | N56: Regular | O56: Regular | P56: 0 | Q56: OK | R56: M | S56: 1930 | T56: 2000 | Z56: 0 | AA56: 1 | AB56: 0 | AC56: 0 | AF56: 1967 | AG56: 1992 | AO56: TRUE | AP56: USA | AQ56: 1973 | AR56: 2016 | AS56: 43骞?9349 | AT56: 25.596167 | AU56: =ROUND(AT56/365,3) -> 0.07
A57: 55 | B57: BHM-1992 | C57: 3500baa8-3bbd-11e5-afeb-eb6f07f9fec7 | D57: 31 | E57: BHM | F57: =VLOOKUP(E57,country_continent!A:C,2,FALSE) -> The Bahamas | G57: =VLOOKUP(E57,country_continent!A:C,3,FALSE) -> North America | H57: Ingraham | I57: 33837 | J57: =IF(ISNUMBER(SEARCH("-", I57)), SUBSTITUTE(I57, "-", "/"), I57) -> 33837 | K57: 37379 | L57: =IF(ISNUMBER(SEARCH("-", K57)), SUBSTITUTE(K57, "-", "/"), K57) -> 37379 | M57: Regular | N57: Regular | O57: Regular | P57: 0 | Q57: OK | R57: M | S57: 1947 | T57: -777 | Y57: https://urldefense.proofpoint.com/v2/url?u=http-3A__dbpedia.org_resource_Hubert-5FIngraham&d=BQID-g&c=kbmfwr1Yojg42sGEpaQh5ofMHBeTl9EI2eaqQZhHbOU&r=ZliGVSRwfirWoETOrKCh2RSnoygzVPWEk95Me9L-Kwo&m=EaKyFx9mpkhPdFxsxzvW_fiM3jbYwM3xYLjVbSFoDAg&s=aovuCrjZcQLSygcYa6DQX-V8liSJDbOedpmr_d0NAJA&e= | Z57: 0 | AA57: 1 | AB57: 0 | AC57: 0 | AF57: 1992 | AG57: 2002 | AO57: TRUE | AP57: USA | AQ57: 1973 | AR57: 2016 | AS57: 43骞?3542 | AT57: 9.6974675 | AU57: =ROUND(AT57/365,3) -> 0.027
A58: 56 | B58: BHM-2002 | C58: 81deda9d-1e42-11e4-b4cd-db5882bf8def | D58: 31 | E58: BHM | F58: =VLOOKUP(E58,country_continent!A:C,2,FALSE) -> The Bahamas | G58: =VLOOKUP(E58,country_continent!A:C,3,FALSE) -> North America | H58: Christie | I58: 37379 | J58: =IF(ISNUMBER(SEARCH("-", I58)), SUBSTITUTE(I58, "-", "/"), I58) -> 37379 | K58: 38476 | L58: =IF(ISNUMBER(SEARCH("-", K58)), SUBSTITUTE(K58, "-", "/"), K58) -> 38476 | M58: Regular | N58: Regular | O58: Regular | P58: 0 | Q58: OK | R58: M | S58: 1943 | T58: -777 | Z58: 0 | AA58: 1 | AB58: 0 | AC58: 0 | AF58: 2002 | AG58: 2005 | AO58: TRUE | AP58: USA | AQ58: 1973 | AR58: 2016 | AS58: 43骞?1097 | AT58: 3.0034223 | AU58: =ROUND(AT58/365,3) -> 0.008
A59: 57 | B59: BHM-2005-1 | C59: 824ff7ff-1e42-11e4-b4cd-db5882bf8def | D59: 31 | E59: BHM | F59: =VLOOKUP(E59,country_continent!A:C,2,FALSE) -> The Bahamas | G59: =VLOOKUP(E59,country_continent!A:C,3,FALSE) -> North America | H59: Cynthia A. Pratt | I59: 38476 | J59: =IF(ISNUMBER(SEARCH("-", I59)), SUBSTITUTE(I59, "-", "/"), I59) -> 38476 | K59: 38525 | L59: =IF(ISNUMBER(SEARCH("-", K59)), SUBSTITUTE(K59, "-", "/"), K59) -> 38525 | M59: Regular | N59: Regular | O59: Regular | P59: 0 | Q59: OK | R59: F | S59: 1943 | T59: -777 | Z59: 0 | AA59: 1 | AB59: 0 | AC59: 0 | AF59: 2005 | AG59: 2005 | AO59: TRUE | AP59: USA | AQ59: 1973 | AR59: 2016 | AS59: 43骞?49 | AT59: 0.13415469 | AU59: =ROUND(AT59/365,3) -> 0
A60: 58 | B60: BHM-2005-2 | C60: 81deda9d-1e42-11e4-b4cd-db5882bf8def | D60: 31 | E60: BHM | F60: =VLOOKUP(E60,country_continent!A:C,2,FALSE) -> The Bahamas | G60: =VLOOKUP(E60,country_continent!A:C,3,FALSE) -> North America | H60: Christie | I60: 38525 | J60: =IF(ISNUMBER(SEARCH("-", I60)), SUBSTITUTE(I60, "-", "/"), I60) -> 38525 | K60: 39206 | L60: =IF(ISNUMBER(SEARCH("-", K60)), SUBSTITUTE(K60, "-", "/"), K60) -> 39206 | M60: Regular | N60: Regular | O60: Regular | P60: 1 | Q60: OK | R60: M | S60: 1943 | T60: -777 | Z60: 0 | AA60: 1 | AB60: 0 | AC60: 0 | AF60: 2005 | AG60: 2007 | AO60: TRUE | AP60: USA | AQ60: 1973 | AR60: 2016 | AS60: 43骞?681 | AT60: 1.8644764 | AU60: =ROUND(AT60/365,3) -> 0.005
A61: 59 | B61: BHM-2007 | C61: 3500baa8-3bbd-11e5-afeb-eb6f07f9fec7 | D61: 31 | E61: BHM | F61: =VLOOKUP(E61,country_continent!A:C,2,FALSE) -> The Bahamas | G61: =VLOOKUP(E61,country_continent!A:C,3,FALSE) -> North America | H61: Ingraham | I61: 39206 | J61: =IF(ISNUMBER(SEARCH("-", I61)), SUBSTITUTE(I61, "-", "/"), I61) -> 39206 | K61: 41037 | L61: =IF(ISNUMBER(SEARCH("-", K61)), SUBSTITUTE(K61, "-", "/"), K61) -> 41037 | M61: Regular | N61: Regular | O61: Regular | P61: 1 | Q61: OK | R61: M | S61: 1947 | T61: -777 | Z61: 0 | AA61: 1 | AB61: 0 | AC61: 0 | AF61: 2007 | AG61: 2012 | AO61: TRUE | AP61: USA | AQ61: 1973 | AR61: 2016 | AS61: 43骞?1831 | AT61: 5.0130048 | AU61: =ROUND(AT61/365,3) -> 0.014
A62: 60 | B62: BHM-2012 | C62: 81deda9d-1e42-11e4-b4cd-db5882bf8def | D62: 31 | E62: BHM | F62: =VLOOKUP(E62,country_continent!A:C,2,FALSE) -> The Bahamas | G62: =VLOOKUP(E62,country_continent!A:C,3,FALSE) -> North America | H62: Christie | I62: 41037 | J62: =IF(ISNUMBER(SEARCH("-", I62)), SUBSTITUTE(I62, "-", "/"), I62) -> 41037 | K62: 42369 | L62: =IF(ISNUMBER(SEARCH("-", K62)), SUBSTITUTE(K62, "-", "/"), K62) -> 42369 | M62: Regular | N62: Still in Office | O62: Still in Office | P62: 2 | Q62: Leader Still in Office | R62: M | S62: 1943 | T62: -777 | U62: 15939 | V62: 15939 | Z62: 0 | AA62: -888 | AB62: -888 | AC62: -888 | AF62: 2012 | AG62: 2015 | AO62: TRUE | AP62: USA | AQ62: 1973 | AR62: 2016 | AS62: 43骞?1332 | AT62: 3.6468172 | AU62: =ROUND(AT62/365,3) -> 0.01
A63: 61 | B63: CUB-1902 | C63: 81deda9e-1e42-11e4-b4cd-db5882bf8def | D63: 40 | E63: CUB | F63: =VLOOKUP(E63,country_continent!A:C,2,FALSE) -> Cuba | G63: =VLOOKUP(E63,country_continent!A:C,3,FALSE) -> North America | H63: Palma | I63: 871 | J63: =IF(ISNUMBER(SEARCH("-", I63)), SUBSTITUTE(I63, "-", "/"), I63) -> 871 | K63: 2463 | L63: =IF(ISNUMBER(SEARCH("-", K63)), SUBSTITUTE(K63, "-", "/"), K63) -> 2463 | M63: Regular | N63: Irregular | O63: Unknown | P63: 0 | Q63: OK | R63: M | S63: 1835 | T63: 1908 | U63: 1835-07-09 | V63: 09jul1835 | Z63: 0 | AA63: 3 | AB63: -999 | AC63: 0 | AF63: 1902 | AG63: 1906 | AO63: TRUE | AP63: USA | AQ63: 1916 | AR63: 2016 | AS63: 100骞?1592 | AT63: 4.3586585 | AU63: =ROUND(AT63/365,3) -> 0.012
A64: 62 | B64: CUB-1909 | C64: 81deda9f-1e42-11e4-b4cd-db5882bf8def | D64: 40 | E64: CUB | F64: =VLOOKUP(E64,country_continent!A:C,2,FALSE) -> Cuba | G64: =VLOOKUP(E64,country_continent!A:C,3,FALSE) -> North America | H64: Gomez | I64: 3316 | J64: =IF(ISNUMBER(SEARCH("-", I64)), SUBSTITUTE(I64, "-", "/"), I64) -> 3316 | K64: 4889 | L64: =IF(ISNUMBER(SEARCH("-", K64)), SUBSTITUTE(K64, "-", "/"), K64) -> 4889 | M64: Regular | N64: Regular | O64: Regular | P64: 0 | Q64: OK | R64: M | S64: 1858 | T64: 1921 | U64: 1858-07-06 | V64: 06jul1858 | Y64: https://urldefense.proofpoint.com/v2/url?u=http-3A__dbpedia.org_resource_Jos-25C3-25A9-5FMiguel-5FG-25C3-25B3mez&d=BQID-g&c=kbmfwr1Yojg42sGEpaQh5ofMHBeTl9EI2eaqQZhHbOU&r=ZliGVSRwfirWoETOrKCh2RSnoygzVPWEk95Me9L-Kwo&m=EaKyFx9mpkhPdFxsxzvW_fiM3jbYwM3xYLjVbSFoDAg&s=1NF5x1Zu_N6SeSZ0Sl-F8t5Jd6hSEWbXstJtm8tflaw&e= | Z64: 0 | AA64: 1 | AB64: 0 | AC64: 0 | AD64: Father of Gomez y Arias%81df3c45-1e42-11e4-b4cd-db5882bf8def | AE64: 0 | AF64: 1909 | AG64: 1913 | AO64: TRUE | AP64: USA | AQ64: 1916 | AR64: 2016 | AS64: 100骞?1573 | AT64: 4.3066393 | AU64: =ROUND(AT64/365,3) -> 0.012
A65: 63 | B65: CUB-1913 | C65: 81dedaa0-1e42-11e4-b4cd-db5882bf8def | D65: 40 | E65: CUB | F65: =VLOOKUP(E65,country_continent!A:C,2,FALSE) -> Cuba | G65: =VLOOKUP(E65,country_continent!A:C,3,FALSE) -> North America | H65: Menocal | I65: 4889 | J65: =IF(ISNUMBER(SEARCH("-", I65)), SUBSTITUTE(I65, "-", "/"), I65) -> 4889 | K65: 7811 | L65: =IF(ISNUMBER(SEARCH("-", K65)), SUBSTITUTE(K65, "-", "/"), K65) -> 7811 | M65: Regular | N65: Regular | O65: Regular | P65: 0 | Q65: Exile | R65: M | S65: 1868 | T65: 1941 | U65: 1868-12-17 | V65: 17dec1868 | Z65: 0 | AA65: 1 | AB65: 0 | AC65: 1 | AF65: 1913 | AG65: 1921 | AO65: TRUE | AP65: USA | AQ65: 1916 | AR65: 2016 | AS65: 100骞?2922 | AT65: 8 | AU65: =ROUND(AT65/365,3) -> 0.022
A66: 64 | B66: CUB-1921 | C66: 81df0b70-1e42-11e4-b4cd-db5882bf8def | D66: 40 | E66: CUB | F66: =VLOOKUP(E66,country_continent!A:C,2,FALSE) -> Cuba | G66: =VLOOKUP(E66,country_continent!A:C,3,FALSE) -> North America | H66: Zyas y Alfonso | I66: 7811 | J66: =IF(ISNUMBER(SEARCH("-", I66)), SUBSTITUTE(I66, "-", "/"), I66) -> 7811 | K66: 9272 | L66: =IF(ISNUMBER(SEARCH("-", K66)), SUBSTITUTE(K66, "-", "/"), K66) -> 9272 | M66: Regular | N66: Regular | O66: Regular | P66: 0 | Q66: OK | R66: M | S66: 1861 | T66: 1934 | U66: 1861-09-21 | V66: 21sep1861 | Y66: https://urldefense.proofpoint.com/v2/url?u=http-3A__dbpedia.org_resource_Alfredo-5FZayas-5Fy-5FAlfonso&d=BQID-g&c=kbmfwr1Yojg42sGEpaQh5ofMHBeTl9EI2eaqQZhHbOU&r=ZliGVSRwfirWoETOrKCh2RSnoygzVPWEk95Me9L-Kwo&m=EaKyFx9mpkhPdFxsxzvW_fiM3jbYwM3xYLjVbSFoDAg&s=qVE_rcLPA754FWe1nuWY7rwfVNVECGVzH49nyW6jN_s&e= | Z66: 0 | AA66: 1 | AB66: 0 | AC66: 0 | AF66: 1921 | AG66: 1925 | AO66: TRUE | AP66: USA | AQ66: 1916 | AR66: 2016 | AS66: 100骞?1461 | AT66: 4 | AU66: =ROUND(AT66/365,3) -> 0.011
A67: 65 | B67: CUB-1925 | C67: 81df0b71-1e42-11e4-b4cd-db5882bf8def | D67: 40 | E67: CUB | F67: =VLOOKUP(E67,country_continent!A:C,2,FALSE) -> Cuba | G67: =VLOOKUP(E67,country_continent!A:C,3,FALSE) -> North America | H67: Machado Morales | I67: 9272 | J67: =IF(ISNUMBER(SEARCH("-", I67)), SUBSTITUTE(I67, "-", "/"), I67) -> 9272 | K67: 12278 | L67: =IF(ISNUMBER(SEARCH("-", K67)), SUBSTITUTE(K67, "-", "/"), K67) -> 12278 | M67: Regular | N67: Irregular | O67: Removed by Military, without Foreign Support | P67: 0 | Q67: Exile | R67: M | S67: 1871 | T67: 1939 | U67: 1871-09-28 | V67: 28sep1871 | Z67: 0 | AA67: 3 | AB67: 6 | AC67: 1 | AF67: 1925 | AG67: 1933 | AO67: TRUE | AP67: USA | AQ67: 1916 | AR67: 2016 | AS67: 100骞?3006 | AT67: 8.2299795 | AU67: =ROUND(AT67/365,3) -> 0.023
A68: 66 | B68: CUB-1933-1 | C68: 81df0b72-1e42-11e4-b4cd-db5882bf8def | D68: 40 | E68: CUB | F68: =VLOOKUP(E68,country_continent!A:C,2,FALSE) -> Cuba | G68: =VLOOKUP(E68,country_continent!A:C,3,FALSE) -> North America | H68: de Cespedes | I68: 12278 | J68: =IF(ISNUMBER(SEARCH("-", I68)), SUBSTITUTE(I68, "-", "/"), I68) -> 12278 | K68: 12302 | L68: =IF(ISNUMBER(SEARCH("-", K68)), SUBSTITUTE(K68, "-", "/"), K68) -> 12302 | M68: Irregular | N68: Irregular | O68: Removed by Military, without Foreign Support | P68: 0 | Q68: OK | R68: M | S68: 1871 | T68: 1939 | U68: 1871-08-12 | V68: 12aug1871 | Z68: 1 | AA68: 3 | AB68: 6 | AC68: 0 | AF68: 1933 | AG68: 1933 | AO68: TRUE | AP68: USA | AQ68: 1916 | AR68: 2016 | AS68: 100骞?24 | AT68: 0.065708419 | AU68: =ROUND(AT68/365,3) -> 0
A69: 67 | B69: CUB-1933-2 | C69: 81df0b73-1e42-11e4-b4cd-db5882bf8def | D69: 40 | E69: CUB | F69: =VLOOKUP(E69,country_continent!A:C,2,FALSE) -> Cuba | G69: =VLOOKUP(E69,country_continent!A:C,3,FALSE) -> North America | H69: Grau San Martin | I69: 12307 | J69: =IF(ISNUMBER(SEARCH("-", I69)), SUBSTITUTE(I69, "-", "/"), I69) -> 12307 | K69: 12434 | L69: =IF(ISNUMBER(SEARCH("-", K69)), SUBSTITUTE(K69, "-", "/"), K69) -> 12434 | M69: Irregular | N69: Irregular | O69: Removed in Military Power Struggle Short of Coup | P69: 0 | Q69: Exile | R69: M | S69: 1882 | T69: 1969 | U69: 1882-09-13 | V69: 13sep1882 | Z69: 1 | AA69: 3 | AB69: 16 | AC69: 1 | AF69: 1933 | AG69: 1934 | AO69: TRUE | AP69: USA | AQ69: 1916 | AR69: 2016 | AS69: 100骞?127 | AT69: 0.34770705 | AU69: =ROUND(AT69/365,3) -> 0.001
A70: 68 | B70: CUB-1934-1 | C70: 81df0b74-1e42-11e4-b4cd-db5882bf8def | D70: 40 | E70: CUB | F70: =VLOOKUP(E70,country_continent!A:C,2,FALSE) -> Cuba | G70: =VLOOKUP(E70,country_continent!A:C,3,FALSE) -> North America | H70: Hevia | I70: 12434 | J70: =IF(ISNUMBER(SEARCH("-", I70)), SUBSTITUTE(I70, "-", "/"), I70) -> 12434 | K70: 12437 | L70: =IF(ISNUMBER(SEARCH("-", K70)), SUBSTITUTE(K70, "-", "/"), K70) -> 12437 | M70: Irregular | N70: Irregular | O70: Removed in Military Power Struggle Short of Coup | P70: 0 | Q70: OK | R70: M | S70: 1900 | T70: 1964 | Y70: https://urldefense.proofpoint.com/v2/url?u=http-3A__dbpedia.org_resource_Carlos-5FHevia&d=BQID-g&c=kbmfwr1Yojg42sGEpaQh5ofMHBeTl9EI2eaqQZhHbOU&r=ZliGVSRwfirWoETOrKCh2RSnoygzVPWEk95Me9L-Kwo&m=EaKyFx9mpkhPdFxsxzvW_fiM3jbYwM3xYLjVbSFoDAg&s=5-6e0ciWg-SlbSXQhsIrBVVl7sydg_gVQjoic3YQiQE&e= | Z70: 1 | AA70: 3 | AB70: 16 | AC70: 0 | AF70: 1934 | AG70: 1934 | AO70: TRUE | AP70: USA | AQ70: 1916 | AR70: 2016 | AS70: 100骞?3 | AT70: 0.0082135524 | AU70: =ROUND(AT70/365,3) -> 0
A71: 69 | B71: CUB-1934-2 | C71: 81df0b75-1e42-11e4-b4cd-db5882bf8def | D71: 40 | E71: CUB | F71: =VLOOKUP(E71,country_continent!A:C,2,FALSE) -> Cuba | G71: =VLOOKUP(E71,country_continent!A:C,3,FALSE) -> North America | H71: Mendieta | I71: 12437 | J71: =IF(ISNUMBER(SEARCH("-", I71)), SUBSTITUTE(I71, "-", "/"), I71) -> 12437 | K71: 13130 | L71: =IF(ISNUMBER(SEARCH("-", K71)), SUBSTITUTE(K71, "-", "/"), K71) -> 13130 | M71: Irregular | N71: Regular | O71: Regular | P71: 0 | Q71: OK | R71: M | S71: 1873 | T71: 1960 | U71: 1873-11-04 | V71: 04nov1873 | Z71: 1 | AA71: 1 | AB71: 0 | AC71: 0 | AF71: 1934 | AG71: 1935 | AO71: TRUE | AP71: USA | AQ71: 1916 | AR71: 2016 | AS71: 100骞?693 | AT71: 1.8973306 | AU71: =ROUND(AT71/365,3) -> 0.005
A72: 70 | B72: CUB-1935 | C72: 81df3c44-1e42-11e4-b4cd-db5882bf8def | D72: 40 | E72: CUB | F72: =VLOOKUP(E72,country_continent!A:C,2,FALSE) -> Cuba | G72: =VLOOKUP(E72,country_continent!A:C,3,FALSE) -> North America | H72: Barnet | I72: 13130 | J72: =IF(ISNUMBER(SEARCH("-", I72)), SUBSTITUTE(I72, "-", "/"), I72) -> 13130 | K72: 13290 | L72: =IF(ISNUMBER(SEARCH("-", K72)), SUBSTITUTE(K72, "-", "/"), K72) -> 13290 | M72: Regular | N72: Regular | O72: Regular | P72: 0 | Q72: OK | R72: M | S72: 1864 | T72: 1945 | Z72: 0 | AA72: 1 | AB72: 0 | AC72: 0 | AF72: 1935 | AG72: 1936 | AO72: TRUE | AP72: USA | AQ72: 1916 | AR72: 2016 | AS72: 100骞?160 | AT72: 0.43805613 | AU72: =ROUND(AT72/365,3) -> 0.001
A73: 71 | B73: CUB-1936-1 | C73: 81df3c45-1e42-11e4-b4cd-db5882bf8def | D73: 40 | E73: CUB | F73: =VLOOKUP(E73,country_continent!A:C,2,FALSE) -> Cuba | G73: =VLOOKUP(E73,country_continent!A:C,3,FALSE) -> North America | H73: Gomez y Arias | I73: 13290 | J73: =IF(ISNUMBER(SEARCH("-", I73)), SUBSTITUTE(I73, "-", "/"), I73) -> 13290 | K73: 13512 | L73: =IF(ISNUMBER(SEARCH("-", K73)), SUBSTITUTE(K73, "-", "/"), K73) -> 13512 | M73: Regular | N73: Regular | O73: Regular | P73: 0 | Q73: OK | R73: M | S73: 1889 | T73: 1950 | U73: 1889-10-06 | V73: 06oct1889 | Z73: 0 | AA73: 1 | AB73: 0 | AC73: 0 | AD73: Son of Gomez%81deda9f-1e42-11e4-b4cd-db5882bf8def | AE73: 1 | AF73: 1936 | AG73: 1936 | AO73: TRUE | AP73: USA | AQ73: 1916 | AR73: 2016 | AS73: 100骞?222 | AT73: 0.60780287 | AU73: =ROUND(AT73/365,3) -> 0.002
A74: 72 | B74: CUB-1936-2 | C74: 81df3c46-1e42-11e4-b4cd-db5882bf8def | D74: 40 | E74: CUB | F74: =VLOOKUP(E74,country_continent!A:C,2,FALSE) -> Cuba | G74: =VLOOKUP(E74,country_continent!A:C,3,FALSE) -> North America | H74: Laredo Bru | I74: 13512 | J74: =IF(ISNUMBER(SEARCH("-", I74)), SUBSTITUTE(I74, "-", "/"), I74) -> 13512 | K74: 14894 | L74: =IF(ISNUMBER(SEARCH("-", K74)), SUBSTITUTE(K74, "-", "/"), K74) -> 14894 | M74: Regular | N74: Regular | O74: Regular | P74: 0 | Q74: OK | R74: M | S74: 1875 | T74: 1946 | U74: 1875-04-23 | V74: 23apr1875 | Y74: https://urldefense.proofpoint.com/v2/url?u=http-3A__dbpedia.org_resource_Federico-5FLaredo-5FBr-25C3-25BA&d=BQID-g&c=kbmfwr1Yojg42sGEpaQh5ofMHBeTl9EI2eaqQZhHbOU&r=ZliGVSRwfirWoETOrKCh2RSnoygzVPWEk95Me9L-Kwo&m=EaKyFx9mpkhPdFxsxzvW_fiM3jbYwM3xYLjVbSFoDAg&s=Rq7KVvMy39C5SnmdtY7Gu0C2BRV1pS8qMybPSXwET2w&e= | Z74: 0 | AA74: 1 | AB74: 0 | AC74: 0 | AF74: 1936 | AG74: 1940 | AO74: TRUE | AP74: USA | AQ74: 1916 | AR74: 2016 | AS74: 100骞?1382 | AT74: 3.7837098 | AU74: =ROUND(AT74/365,3) -> 0.01
A75: 73 | B75: CUB-1940 | C75: 81df3c47-1e42-11e4-b4cd-db5882bf8def | D75: 40 | E75: CUB | F75: =VLOOKUP(E75,country_continent!A:C,2,FALSE) -> Cuba | G75: =VLOOKUP(E75,country_continent!A:C,3,FALSE) -> North America | H75: Batista | I75: 14894 | J75: =IF(ISNUMBER(SEARCH("-", I75)), SUBSTITUTE(I75, "-", "/"), I75) -> 14894 | K75: 16355 | L75: =IF(ISNUMBER(SEARCH("-", K75)), SUBSTITUTE(K75, "-", "/"), K75) -> 16355 | M75: Regular | N75: Regular | O75: Regular | P75: 0 | Q75: Exile | R75: M | S75: 1901 | T75: 1973 | U75: 382 | V75: 382 | Y75: https://urldefense.proofpoint.com/v2/url?u=http-3A__dbpedia.org_resource_Fulgencio-5FBatista&d=BQID-g&c=kbmfwr1Yojg42sGEpaQh5ofMHBeTl9EI2eaqQZhHbOU&r=ZliGVSRwfirWoETOrKCh2RSnoygzVPWEk95Me9L-Kwo&m=EaKyFx9mpkhPdFxsxzvW_fiM3jbYwM3xYLjVbSFoDAg&s=BNGdwp9997BWodyXCQgGf6XkYdL6Qru7kZypNW4NmjE&e= | Z75: 0 | AA75: 1 | AB75: 0 | AC75: 1 | AF75: 1940 | AG75: 1944 | AO75: TRUE | AP75: USA | AQ75: 1916 | AR75: 2016 | AS75: 100骞?1461 | AT75: 4 | AU75: =ROUND(AT75/365,3) -> 0.011
A76: 74 | B76: CUB-1944 | C76: 81df0b73-1e42-11e4-b4cd-db5882bf8def | D76: 40 | E76: CUB | F76: =VLOOKUP(E76,country_continent!A:C,2,FALSE) -> Cuba | G76: =VLOOKUP(E76,country_continent!A:C,3,FALSE) -> North America | H76: Grau San Martin | I76: 16355 | J76: =IF(ISNUMBER(SEARCH("-", I76)), SUBSTITUTE(I76, "-", "/"), I76) -> 16355 | K76: 17816 | L76: =IF(ISNUMBER(SEARCH("-", K76)), SUBSTITUTE(K76, "-", "/"), K76) -> 17816 | M76: Regular | N76: Regular | O76: Regular | P76: 1 | Q76: Exile | R76: M | S76: 1882 | T76: 1969 | U76: 1882-09-13 | V76: 13sep1882 | Z76: 0 | AA76: 1 | AB76: 0 | AC76: 1 | AF76: 1944 | AG76: 1948 | AN76: 3 | AO76: TRUE | AP76: USA | AQ76: 1916 | AR76: 2016 | AS76: 100骞?1461 | AT76: 4 | AU76: =ROUND(AT76/365,3) -> 0.011
A77: 75 | B77: CUB-1948 | C77: 81df3c48-1e42-11e4-b4cd-db5882bf8def | D77: 40 | E77: CUB | F77: =VLOOKUP(E77,country_continent!A:C,2,FALSE) -> Cuba | G77: =VLOOKUP(E77,country_continent!A:C,3,FALSE) -> North America | H77: Prio Socarres | I77: 17816 | J77: =IF(ISNUMBER(SEARCH("-", I77)), SUBSTITUTE(I77, "-", "/"), I77) -> 17816 | K77: 19063 | L77: =IF(ISNUMBER(SEARCH("-", K77)), SUBSTITUTE(K77, "-", "/"), K77) -> 19063 | M77: Regular | N77: Irregular | O77: Removed by Military, without Foreign Support | P77: 0 | Q77: Exile | R77: M | S77: 1903 | T77: 1977 | U77: 1291 | V77: 1291 | Y77: https://urldefense.proofpoint.com/v2/url?u=http-3A__dbpedia.org_resource_Carlos-5FPr-25C3-25ADo-5FSocarr-25C3-25A1s&d=BQID-g&c=kbmfwr1Yojg42sGEpaQh5ofMHBeTl9EI2eaqQZhHbOU&r=ZliGVSRwfirWoETOrKCh2RSnoygzVPWEk95Me9L-Kwo&m=EaKyFx9mpkhPdFxsxzvW_fiM3jbYwM3xYLjVbSFoDAg&s=hVl4y-cioCjN1XnAMbuYYzgzAymI-wcT2czvmgVhZhE&e= | Z77: 0 | AA77: 3 | AB77: 6 | AC77: 1 | AF77: 1948 | AG77: 1952 | AN77: 2.4 | AO77: TRUE | AP77: USA | AQ77: 1916 | AR77: 2016 | AS77: 100骞?1247 | AT77: 3.4140999 | AU77: =ROUND(AT77/365,3) -> 0.009
A78: 76 | B78: CUB-1952 | C78: 81df3c47-1e42-11e4-b4cd-db5882bf8def | D78: 40 | E78: CUB | F78: =VLOOKUP(E78,country_continent!A:C,2,FALSE) -> Cuba | G78: =VLOOKUP(E78,country_continent!A:C,3,FALSE) -> North America | H78: Batista | I78: 19063 | J78: =IF(ISNUMBER(SEARCH("-", I78)), SUBSTITUTE(I78, "-", "/"), I78) -> 19063 | K78: 21551 | L78: =IF(ISNUMBER(SEARCH("-", K78)), SUBSTITUTE(K78, "-", "/"), K78) -> 21551 | M78: Irregular | N78: Irregular | O78: Removed by Rebels, without Foreign Support | P78: 1 | Q78: Exile | R78: M | S78: 1901 | T78: 1973 | U78: 382 | V78: 382 | Y78: https://urldefense.proofpoint.com/v2/url?u=http-3A__dbpedia.org_resource_Fulgencio-5FBatista&d=BQID-g&c=kbmfwr1Yojg42sGEpaQh5ofMHBeTl9EI2eaqQZhHbOU&r=ZliGVSRwfirWoETOrKCh2RSnoygzVPWEk95Me9L-Kwo&m=EaKyFx9mpkhPdFxsxzvW_fiM3jbYwM3xYLjVbSFoDAg&s=BNGdwp9997BWodyXCQgGf6XkYdL6Qru7kZypNW4NmjE&e= | Z78: 1 | AA78: 3 | AB78: 4 | AC78: 1 | AF78: 1952 | AG78: 1959 | AN78: -5.62 | AO78: TRUE | AP78: USA | AQ78: 1916 | AR78: 2016 | AS78: 100骞?2488 | AT78: 6.8117728 | AU78: =ROUND(AT78/365,3) -> 0.019
A79: 77 | B79: CUB-1959 | C79: 81df6d18-1e42-11e4-b4cd-db5882bf8def | D79: 40 | E79: CUB | F79: =VLOOKUP(E79,country_continent!A:C,2,FALSE) -> Cuba | G79: =VLOOKUP(E79,country_continent!A:C,3,FALSE) -> North America | H79: Castro | I79: 21552 | J79: =IF(ISNUMBER(SEARCH("-", I79)), SUBSTITUTE(I79, "-", "/"), I79) -> 21552 | K79: 39502 | L79: =IF(ISNUMBER(SEARCH("-", K79)), SUBSTITUTE(K79, "-", "/"), K79) -> 39502 | M79: Irregular | N79: Retired Due to Ill Health | O79: Regular | P79: 0 | Q79: OK | R79: M | S79: 1927 | T79: -777 | U79: 10087 | V79: 10087 | Z79: 1 | AA79: 2.0999999 | AB79: 0 | AC79: 0 | AD79: Brother of Raul Castro%824ff801-1e42-11e4-b4cd-db5882bf8def | AE79: 0 | AF79: 1959 | AG79: 2008 | AH79: 2.6155997 | AI79: 2487.027 | AJ79: 3.4418878 | AK79: 22.277551 | AL79: 0.92649441 | AM79: 1.27245 | AN79: -6.8 | AO79: TRUE | AP79: USA | AQ79: 1916 | AR79: 2016 | AS79: 100骞?17950 | AT79: 49.144422 | AU79: =ROUND(AT79/365,3) -> 0.135
A80: 78 | B80: CUB-2008 | C80: 824ff801-1e42-11e4-b4cd-db5882bf8def | D80: 40 | E80: CUB | F80: =VLOOKUP(E80,country_continent!A:C,2,FALSE) -> Cuba | G80: =VLOOKUP(E80,country_continent!A:C,3,FALSE) -> North America | H80: Raul Castro | I80: 39502 | J80: =IF(ISNUMBER(SEARCH("-", I80)), SUBSTITUTE(I80, "-", "/"), I80) -> 39502 | K80: 42369 | L80: =IF(ISNUMBER(SEARCH("-", K80)), SUBSTITUTE(K80, "-", "/"), K80) -> 42369 | M80: Regular | N80: Still in Office | O80: Still in Office | P80: 0 | Q80: Leader Still in Office | R80: M | S80: 1931 | T80: -777 | U80: 11477 | V80: 11477 | Z80: 0 | AA80: -888 | AB80: -888 | AC80: -888 | AD80: Brother of Castro%81df6d18-1e42-11e4-b4cd-db5882bf8def | AF80: 2008 | AG80: 2015 | AH80: 2.7650102 | AI80: 5965 | AJ80: 2.2862213 | AK80: 6.15 | AL80: -0.013525861 | AM80: 2.1034821 | AN80: -7 | AO80: TRUE | AP80: USA | AQ80: 1916 | AR80: 2016 | AS80: 100骞?2867 | AT80: 7.8494182 | AU80: =ROUND(AT80/365,3) -> 0.022
A81: 79 | B81: HAI-1874 | C81: 81df6d19-1e42-11e4-b4cd-db5882bf8def | D81: 41 | E81: HAI | F81: =VLOOKUP(E81,country_continent!A:C,2,FALSE) -> Haiti | G81: =VLOOKUP(E81,country_continent!A:C,3,FALSE) -> North America | H81: Rameau | I81: 1874-06-11 | J81: =IF(ISNUMBER(SEARCH("-", I81)), SUBSTITUTE(I81, "-", "/"), I81) -> 1874/06/11 | K81: 1876-04-15 | L81: =IF(ISNUMBER(SEARCH("-", K81)), SUBSTITUTE(K81, "-", "/"), K81) -> 1876/04/15 | M81: Irregular | N81: Irregular | O81: Removed by Military, without Foreign Support | P81: 0 | Q81: Death | R81: M | S81: 1828 | T81: 1876 | W81: 1876-04-15 | X81: 15apr1876 | Z81: 1 | AA81: 3 | AB81: 6 | AC81: 3 | AF81: 1874 | AG81: 1876 | AO81: TRUE | AP81: USA | AQ81: 1934 | AR81: 2016 | AS81: 82骞?674 | AT81: 1.8453114 | AU81: =ROUND(AT81/365,3) -> 0.005
A82: 80 | B82: HAI-1876 | C82: 81df6d1a-1e42-11e4-b4cd-db5882bf8def | D82: 41 | E82: HAI | F82: =VLOOKUP(E82,country_continent!A:C,2,FALSE) -> Haiti | G82: =VLOOKUP(E82,country_continent!A:C,3,FALSE) -> North America | H82: Canal | I82: 1876-04-23 | J82: =IF(ISNUMBER(SEARCH("-", I82)), SUBSTITUTE(I82, "-", "/"), I82) -> 1876/04/23 | K82: 1879-07-17 | L82: =IF(ISNUMBER(SEARCH("-", K82)), SUBSTITUTE(K82, "-", "/"), K82) -> 1879/07/17 | M82: Irregular | N82: Irregular | O82: Unknown | P82: 0 | Q82: Exile | R82: M | S82: 1832 | T82: 1905 | Z82: 1 | AA82: 3 | AB82: -999 | AC82: 1 | AF82: 1876 | AG82: 1879 | AO82: TRUE | AP82: USA | AQ82: 1934 | AR82: 2016 | AS82: 82骞?1180 | AT82: 3.2306639 | AU82: =ROUND(AT82/365,3) -> 0.009
A83: 81 | B83: HAI-1879-1 | C83: 81df6d1b-1e42-11e4-b4cd-db5882bf8def | D83: 41 | E83: HAI | F83: =VLOOKUP(E83,country_continent!A:C,2,FALSE) -> Haiti | G83: =VLOOKUP(E83,country_continent!A:C,3,FALSE) -> North America | H83: Herrise | I83: 1879-07-17 | J83: =IF(ISNUMBER(SEARCH("-", I83)), SUBSTITUTE(I83, "-", "/"), I83) -> 1879/07/17 | K83: 1879-07-26 | L83: =IF(ISNUMBER(SEARCH("-", K83)), SUBSTITUTE(K83, "-", "/"), K83) -> 1879/07/26 | M83: Irregular | N83: Regular | O83: Regular | P83: 0 | Q83: Imprisonment | R83: M | S83: -999 | T83: -999 | Z83: 1 | AA83: 1 | AB83: 0 | AC83: 2 | AF83: 1879 | AG83: 1879 | AO83: TRUE | AP83: USA | AQ83: 1934 | AR83: 2016 | AS83: 82骞?9 | AT83: 0.024640657 | AU83: =ROUND(AT83/365,3) -> 0
A84: 82 | B84: HAI-1879-2 | C84: 81df6d1c-1e42-11e4-b4cd-db5882bf8def | D84: 41 | E84: HAI | F84: =VLOOKUP(E84,country_continent!A:C,2,FALSE) -> Haiti | G84: =VLOOKUP(E84,country_continent!A:C,3,FALSE) -> North America | H84: Lamothe | I84: 1879-07-26 | J84: =IF(ISNUMBER(SEARCH("-", I84)), SUBSTITUTE(I84, "-", "/"), I84) -> 1879/07/26 | K84: 1879-10-02 | L84: =IF(ISNUMBER(SEARCH("-", K84)), SUBSTITUTE(K84, "-", "/"), K84) -> 1879/10/02 | M84: Irregular | N84: Irregular | O84: Unknown | P84: 0 | Q84: Imprisonment | R84: M | S84: -999 | T84: -999 | Z84: 1 | AA84: 3 | AB84: -999 | AC84: 2 | AF84: 1879 | AG84: 1879 | AO84: TRUE | AP84: USA | AQ84: 1934 | AR84: 2016 | AS84: 82骞?68 | AT84: 0.18617385 | AU84: =ROUND(AT84/365,3) -> 0.001
A85: 83 | B85: HAI-1879-3 | C85: 81df9dec-1e42-11e4-b4cd-db5882bf8def | D85: 41 | E85: HAI | F85: =VLOOKUP(E85,country_continent!A:C,2,FALSE) -> Haiti | G85: =VLOOKUP(E85,country_continent!A:C,3,FALSE) -> North America | H85: Salomon | I85: 1879-10-23 | J85: =IF(ISNUMBER(SEARCH("-", I85)), SUBSTITUTE(I85, "-", "/"), I85) -> 1879/10/23 | K85: 1888-08-10 | L85: =IF(ISNUMBER(SEARCH("-", K85)), SUBSTITUTE(K85, "-", "/"), K85) -> 1888/08/10 | M85: Irregular | N85: Irregular | O85: Unknown | P85: 0 | Q85: Exile | R85: M | S85: 1815 | T85: 1888 | Z85: 1 | AA85: 3 | AB85: -999 | AC85: 1 | AD85: Uncle-in-law of P. A. T. Simon%81df9def-1e42-11e4-b4cd-db5882bf8def | AE85: 0 | AF85: 1879 | AG85: 1888 | AO85: TRUE | AP85: USA | AQ85: 1934 | AR85: 2016 | AS85: 82骞?3214 | AT85: 8.7994524 | AU85: =ROUND(AT85/365,3) -> 0.024
A86: 84 | B86: HAI-1888-1 | C86: 81df6d1a-1e42-11e4-b4cd-db5882bf8def | D86: 41 | E86: HAI | F86: =VLOOKUP(E86,country_continent!A:C,2,FALSE) -> Haiti | G86: =VLOOKUP(E86,country_continent!A:C,3,FALSE) -> North America | H86: Canal | I86: 1888-08-10 | J86: =IF(ISNUMBER(SEARCH("-", I86)), SUBSTITUTE(I86, "-", "/"), I86) -> 1888/08/10 | K86: 1888-10-16 | L86: =IF(ISNUMBER(SEARCH("-", K86)), SUBSTITUTE(K86, "-", "/"), K86) -> 1888/10/16 | M86: Irregular | N86: Regular | O86: Regular | P86: 1 | Q86: Exile | R86: M | S86: 1832 | T86: 1905 | Z86: 1 | AA86: 1 | AB86: 0 | AC86: 1 | AF86: 1888 | AG86: 1888 | AO86: TRUE | AP86: USA | AQ86: 1934 | AR86: 2016 | AS86: 82骞?67 | AT86: 0.183436 | AU86: =ROUND(AT86/365,3) -> 0.001
A87: 85 | B87: HAI-1888-2 | C87: 81df9ded-1e42-11e4-b4cd-db5882bf8def | D87: 41 | E87: HAI | F87: =VLOOKUP(E87,country_continent!A:C,2,FALSE) -> Haiti | G87: =VLOOKUP(E87,country_continent!A:C,3,FALSE) -> North America | H87: Legitime | I87: 1888-10-16 | J87: =IF(ISNUMBER(SEARCH("-", I87)), SUBSTITUTE(I87, "-", "/"), I87) -> 1888/10/16 | K87: 1889-08-22 | L87: =IF(ISNUMBER(SEARCH("-", K87)), SUBSTITUTE(K87, "-", "/"), K87) -> 1889/08/22 | M87: Irregular | N87: Irregular | O87: Unknown | P87: 0 | Q87: Exile | R87: M | S87: 1841 | T87: 1935 | Z87: 1 | AA87: 3 | AB87: -999 | AC87: 1 | AF87: 1888 | AG87: 1889 | AO87: TRUE | AP87: USA | AQ87: 1934 | AR87: 2016 | AS87: 82骞?310 | AT87: 0.84873374 | AU87: =ROUND(AT87/365,3) -> 0.002
A88: 86 | B88: HAI-1889 | C88: 81df9dee-1e42-11e4-b4cd-db5882bf8def | D88: 41 | E88: HAI | F88: =VLOOKUP(E88,country_continent!A:C,2,FALSE) -> Haiti | G88: =VLOOKUP(E88,country_continent!A:C,3,FALSE) -> North America | H88: Hippolyte | I88: 1889-08-25 | J88: =IF(ISNUMBER(SEARCH("-", I88)), SUBSTITUTE(I88, "-", "/"), I88) -> 1889/08/25 | K88: 1896-03-24 | L88: =IF(ISNUMBER(SEARCH("-", K88)), SUBSTITUTE(K88, "-", "/"), K88) -> 1896/03/24 | M88: Irregular | N88: Natural Death | O88: Regular | P88: 0 | Q88: Missing: Natural Death within Six Months of Losing Office | R88: M | S88: 1827 | T88: 1896 | Z88: 1 | AA88: 2 | AB88: 0 | AC88: -777 | AF88: 1889 | AG88: 1896 | AO88: TRUE | AP88: USA | AQ88: 1934 | AR88: 2016 | AS88: 82骞?2403 | AT88: 6.5790554 | AU88: =ROUND(AT88/365,3) -> 0.018
A89: 87 | B89: HAI-1896 | C89: 81df9def-1e42-11e4-b4cd-db5882bf8def | D89: 41 | E89: HAI | F89: =VLOOKUP(E89,country_continent!A:C,2,FALSE) -> Haiti | G89: =VLOOKUP(E89,country_continent!A:C,3,FALSE) -> North America | H89: P. A. T. Simon | I89: 1896-03-31 | J89: =IF(ISNUMBER(SEARCH("-", I89)), SUBSTITUTE(I89, "-", "/"), I89) -> 1896/03/31 | K89: 863 | L89: =IF(ISNUMBER(SEARCH("-", K89)), SUBSTITUTE(K89, "-", "/"), K89) -> 863 | M89: Regular | N89: Regular | O89: Regular | P89: 0 | Q89: Exile | R89: M | S89: 1835 | T89: 1916 | Z89: 0 | AA89: 1 | AB89: 0 | AC89: 1 | AD89: Nephew-in-law of Salomon%81df9dec-1e42-11e4-b4cd-db5882bf8def | AE89: 1 | AF89: 1896 | AG89: 1902 | AO89: TRUE | AP89: USA | AQ89: 1934 | AR89: 2016 | AS89: 82骞?2232 | AT89: 6.110883 | AU89: =ROUND(AT89/365,3) -> 0.017
A90: 88 | B90: HAI-1902-1 | C90: 81df6d1a-1e42-11e4-b4cd-db5882bf8def | D90: 41 | E90: HAI | F90: =VLOOKUP(E90,country_continent!A:C,2,FALSE) -> Haiti | G90: =VLOOKUP(E90,country_continent!A:C,3,FALSE) -> North America | H90: Canal | I90: 877 | J90: =IF(ISNUMBER(SEARCH("-", I90)), SUBSTITUTE(I90, "-", "/"), I90) -> 877 | K90: 1082 | L90: =IF(ISNUMBER(SEARCH("-", K90)), SUBSTITUTE(K90, "-", "/"), K90) -> 1082 | M90: Irregular | N90: Irregular | O90: Unknown | P90: 2 | Q90: OK | R90: M | S90: 1832 | T90: 1905 | Z90: 1 | AA90: 3 | AB90: -999 | AC90: 0 | AF90: 1902 | AG90: 1902 | AO90: TRUE | AP90: USA | AQ90: 1934 | AR90: 2016 | AS90: 82骞?205 | AT90: 0.56125941 | AU90: =ROUND(AT90/365,3) -> 0.002
A91: 89 | B91: HAI-1902-2 | C91: 81df9df0-1e42-11e4-b4cd-db5882bf8def | D91: 41 | E91: HAI | F91: =VLOOKUP(E91,country_continent!A:C,2,FALSE) -> Haiti | G91: =VLOOKUP(E91,country_continent!A:C,3,FALSE) -> North America | H91: Nord | I91: 1082 | J91: =IF(ISNUMBER(SEARCH("-", I91)), SUBSTITUTE(I91, "-", "/"), I91) -> 1082 | K91: 3277 | L91: =IF(ISNUMBER(SEARCH("-", K91)), SUBSTITUTE(K91, "-", "/"), K91) -> 3277 | M91: Irregular | N91: Irregular | O91: Unknown | P91: 0 | Q91: Exile | R91: M | S91: 1820 | T91: 1910 | W91: 3774 | X91: 3774 | Y91: https://urldefense.proofpoint.com/v2/url?u=http-3A__dbpedia.org_resource_Pierre-5FNord-5FAlexis&d=BQID-g&c=kbmfwr1Yojg42sGEpaQh5ofMHBeTl9EI2eaqQZhHbOU&r=ZliGVSRwfirWoETOrKCh2RSnoygzVPWEk95Me9L-Kwo&m=EaKyFx9mpkhPdFxsxzvW_fiM3jbYwM3xYLjVbSFoDAg&s=1Dt5NLHJeysWHUmXv4_Vxozdu2sAKlioLRe-ZsS4Wo4&e= | Z91: 1 | AA91: 3 | AB91: -999 | AC91: 1 | AF91: 1902 | AG91: 1908 | AO91: TRUE | AP91: USA | AQ91: 1934 | AR91: 2016 | AS91: 82骞?2195 | AT91: 6.0095825 | AU91: =ROUND(AT91/365,3) -> 0.016
A92: 90 | B92: HAI-1908 | C92: 81dfceca-1e42-11e4-b4cd-db5882bf8def | D92: 41 | E92: HAI | F92: =VLOOKUP(E92,country_continent!A:C,2,FALSE) -> Haiti | G92: =VLOOKUP(E92,country_continent!A:C,3,FALSE) -> North America | H92: A. Simon | I92: 3277 | J92: =IF(ISNUMBER(SEARCH("-", I92)), SUBSTITUTE(I92, "-", "/"), I92) -> 3277 | K92: 4233 | L92: =IF(ISNUMBER(SEARCH("-", K92)), SUBSTITUTE(K92, "-", "/"), K92) -> 4233 | M92: Irregular | N92: Irregular | O92: Unknown | P92: 0 | Q92: Exile | R92: M | S92: 1844 | T92: 1923 | Z92: 1 | AA92: 3 | AB92: -999 | AC92: 1 | AF92: 1908 | AG92: 1911 | AO92: TRUE | AP92: USA | AQ92: 1934 | AR92: 2016 | AS92: 82骞?956 | AT92: 2.6173854 | AU92: =ROUND(AT92/365,3) -> 0.007
A93: 91 | B93: HAI-1911 | C93: 81dfcecb-1e42-11e4-b4cd-db5882bf8def | D93: 41 | E93: HAI | F93: =VLOOKUP(E93,country_continent!A:C,2,FALSE) -> Haiti | G93: =VLOOKUP(E93,country_continent!A:C,3,FALSE) -> North America | H93: Leconte | I93: 4237 | J93: =IF(ISNUMBER(SEARCH("-", I93)), SUBSTITUTE(I93, "-", "/"), I93) -> 4237 | K93: 4604 | L93: =IF(ISNUMBER(SEARCH("-", K93)), SUBSTITUTE(K93, "-", "/"), K93) -> 4604 | M93: Irregular | N93: Irregular | O93: Unknown | P93: 0 | Q93: Death | R93: M | S93: 1854 | T93: 1912 | Z93: 1 | AA93: 3 | AB93: -999 | AC93: 3 | AF93: 1911 | AG93: 1912 | AO93: TRUE | AP93: USA | AQ93: 1934 | AR93: 2016 | AS93: 82骞?367 | AT93: 1.0047912 | AU93: =ROUND(AT93/365,3) -> 0.003
A94: 92 | B94: HAI-1912 | C94: 81dfcecc-1e42-11e4-b4cd-db5882bf8def | D94: 41 | E94: HAI | F94: =VLOOKUP(E94,country_continent!A:C,2,FALSE) -> Haiti | G94: =VLOOKUP(E94,country_continent!A:C,3,FALSE) -> North America | H94: Tancred Auguste | I94: 4604 | J94: =IF(ISNUMBER(SEARCH("-", I94)), SUBSTITUTE(I94, "-", "/"), I94) -> 4604 | K94: 4881 | L94: =IF(ISNUMBER(SEARCH("-", K94)), SUBSTITUTE(K94, "-", "/"), K94) -> 4881 | M94: Irregular | N94: Natural Death | O94: Regular | P94: 0 | Q94: Missing: Natural Death within Six Months of Losing Office | R94: M | S94: 1856 | T94: 1913 | Z94: 1 | AA94: 2 | AB94: 0 | AC94: -777 | AF94: 1912 | AG94: 1913 | AO94: TRUE | AP94: USA | AQ94: 1934 | AR94: 2016 | AS94: 82骞?277 | AT94: 0.75838467 | AU94: =ROUND(AT94/365,3) -> 0.002
A95: 93 | B95: HAI-1913 | C95: 81dfcecd-1e42-11e4-b4cd-db5882bf8def | D95: 41 | E95: HAI | F95: =VLOOKUP(E95,country_continent!A:C,2,FALSE) -> Haiti | G95: =VLOOKUP(E95,country_continent!A:C,3,FALSE) -> North America | H95: Michel Oreste | I95: 4881 | J95: =IF(ISNUMBER(SEARCH("-", I95)), SUBSTITUTE(I95, "-", "/"), I95) -> 4881 | K95: 5141 | L95: =IF(ISNUMBER(SEARCH("-", K95)), SUBSTITUTE(K95, "-", "/"), K95) -> 5141 | M95: Regular | N95: Irregular | O95: Unknown | P95: 0 | Q95: Exile | R95: M | S95: 1859 | T95: 1918 | W95: 6876 | X95: 6876 | Z95: 0 | AA95: 3 | AB95: -999 | AC95: 1 | AF95: 1913 | AG95: 1914 | AO95: TRUE | AP95: USA | AQ95: 1934 | AR95: 2016 | AS95: 82骞?260 | AT95: 0.7118412 | AU95: =ROUND(AT95/365,3) -> 0.002
A96: 94 | B96: HAI-1914-1 | C96: 81dfcece-1e42-11e4-b4cd-db5882bf8def | D96: 41 | E96: HAI | F96: =VLOOKUP(E96,country_continent!A:C,2,FALSE) -> Haiti | G96: =VLOOKUP(E96,country_continent!A:C,3,FALSE) -> North America | H96: Oreste Zamor | I96: 5153 | J96: =IF(ISNUMBER(SEARCH("-", I96)), SUBSTITUTE(I96, "-", "/"), I96) -> 5153 | K96: 5406 | L96: =IF(ISNUMBER(SEARCH("-", K96)), SUBSTITUTE(K96, "-", "/"), K96) -> 5406 | M96: Irregular | N96: Irregular | O96: Unknown | P96: 0 | Q96: Death | R96: M | S96: 1861 | T96: 1915 | Z96: 1 | AA96: 3 | AB96: -999 | AC96: 3 | AF96: 1914 | AG96: 1914 | AO96: TRUE | AP96: USA | AQ96: 1934 | AR96: 2016 | AS96: 82骞?253 | AT96: 0.69267625 | AU96: =ROUND(AT96/365,3) -> 0.002
A97: 95 | B97: HAI-1914-2 | C97: 81dfff9e-1e42-11e4-b4cd-db5882bf8def | D97: 41 | E97: HAI | F97: =VLOOKUP(E97,country_continent!A:C,2,FALSE) -> Haiti | G97: =VLOOKUP(E97,country_continent!A:C,3,FALSE) -> North America | H97: Theodore | I97: 5406 | J97: =IF(ISNUMBER(SEARCH("-", I97)), SUBSTITUTE(I97, "-", "/"), I97) -> 5406 | K97: 5532 | L97: =IF(ISNUMBER(SEARCH("-", K97)), SUBSTITUTE(K97, "-", "/"), K97) -> 5532 | M97: Irregular | N97: Irregular | O97: Unknown | P97: 0 | Q97: Exile | R97: M | S97: 1847 | T97: 1917 | W97: 6223 | X97: 6223 | Z97: 1 | AA97: 3 | AB97: -999 | AC97: 1 | AF97: 1914 | AG97: 1915 | AO97: TRUE | AP97: USA | AQ97: 1934 | AR97: 2016 | AS97: 82骞?126 | AT97: 0.3449692 | AU97: =ROUND(AT97/365,3) -> 0.001
A98: 96 | B98: HAI-1915 | C98: 81dfff9f-1e42-11e4-b4cd-db5882bf8def | D98: 41 | E98: HAI | F98: =VLOOKUP(E98,country_continent!A:C,2,FALSE) -> Haiti | G98: =VLOOKUP(E98,country_continent!A:C,3,FALSE) -> North America | H98: Velbrun-Guillaume | I98: 5542 | J98: =IF(ISNUMBER(SEARCH("-", I98)), SUBSTITUTE(I98, "-", "/"), I98) -> 5542 | K98: 5686 | L98: =IF(ISNUMBER(SEARCH("-", K98)), SUBSTITUTE(K98, "-", "/"), K98) -> 5686 | M98: Irregular | N98: Irregular | O98: Unknown | P98: 0 | Q98: Death | R98: M | S98: 1859 | T98: 1915 | U98: 1859-03-04 | V98: 04mar1859 | W98: 5688 | X98: 5688 | Z98: 1 | AA98: 3 | AB98: -999 | AC98: 3 | AF98: 1915 | AG98: 1915 | AO98: TRUE | AP98: USA | AQ98: 1934 | AR98: 2016 | AS98: 82骞?144 | AT98: 0.39425051 | AU98: =ROUND(AT98/365,3) -> 0.001
A99: 97 | B99: HAI-1934 | C99: 81dfffa0-1e42-11e4-b4cd-db5882bf8def | D99: 41 | E99: HAI | F99: =VLOOKUP(E99,country_continent!A:C,2,FALSE) -> Haiti | G99: =VLOOKUP(E99,country_continent!A:C,3,FALSE) -> North America | H99: Vincent | I99: 12646 | J99: =IF(ISNUMBER(SEARCH("-", I99)), SUBSTITUTE(I99, "-", "/"), I99) -> 12646 | K99: 15111 | L99: =IF(ISNUMBER(SEARCH("-", K99)), SUBSTITUTE(K99, "-", "/"), K99) -> 15111 | M99: Regular | N99: Regular | O99: Regular | P99: 0 | Q99: Exile | R99: M | S99: 1874 | T99: 1959 | W99: 21796 | X99: 21796 | Z99: 0 | AA99: 1 | AB99: 0 | AC99: 1 | AF99: 1934 | AG99: 1941 | AO99: TRUE | AP99: USA | AQ99: 1934 | AR99: 2016 | AS99: 82骞?2465 | AT99: 6.7488022 | AU99: =ROUND(AT99/365,3) -> 0.018
A100: 98 | B100: HAI-1941 | C100: 81dfffa1-1e42-11e4-b4cd-db5882bf8def | D100: 41 | E100: HAI | F100: =VLOOKUP(E100,country_continent!A:C,2,FALSE) -> Haiti | G100: =VLOOKUP(E100,country_continent!A:C,3,FALSE) -> North America | H100: Lescot | I100: 15111 | J100: =IF(ISNUMBER(SEARCH("-", I100)), SUBSTITUTE(I100, "-", "/"), I100) -> 15111 | K100: 16813 | L100: =IF(ISNUMBER(SEARCH("-", K100)), SUBSTITUTE(K100, "-", "/"), K100) -> 16813 | M100: Regular | N100: Irregular | O100: Removed by Military, without Foreign Support | P100: 0 | Q100: Exile | R100: M | S100: 1883 | T100: 1974 | U100: 1883-12-09 | V100: 09dec1883 | W100: 27323 | X100: 27323 | Y100: https://urldefense.proofpoint.com/v2/url?u=http-3A__dbpedia.org_resource_-25C3-2589lie-5FLescot&d=BQID-g&c=kbmfwr1Yojg42sGEpaQh5ofMHBeTl9EI2eaqQZhHbOU&r=ZliGVSRwfirWoETOrKCh2RSnoygzVPWEk95Me9L-Kwo&m=EaKyFx9mpkhPdFxsxzvW_fiM3jbYwM3xYLjVbSFoDAg&s=2L7m68zog2eHfDquMvwwe3dqBRL9odI7l8Ovk5co2fc&e= | Z100: 0 | AA100: 3 | AB100: 6 | AC100: 1 | AF100: 1941 | AG100: 1946 | AO100: TRUE | AP100: USA | AQ100: 1934 | AR100: 2016 | AS100: 82骞?1702 | AT100: 4.659822 | AU100: =ROUND(AT100/365,3) -> 0.013
...

Sheet Sheet1
A1: Unnamed: 0 | B1: obsid | C1: leadid | D1: ccode | E1: idacr | F1: country | G1: continent | H1: leader | I1: startdate | J1: startdate_new | K1: enddate | L1: enddate_new | M1: entry | N1: exit | O1: exitcode | P1: prevtimesinoffice | Q1: posttenurefate | R1: gender | S1: yrborn | T1: yrdied | U1: borndate | V1: ebirthdate | W1: deathdate | X1: edeathdate | Y1: dbpediauri | Z1: numentry | AA1: numexit | AB1: numexitcode | AC1: numposttenurefate | AD1: fties | AE1: ftcur | AF1: start_year | AG1: end_year | AH1: avg_gdp_growth | AI1: avg_gni_per_capita | AJ1: avg_inflation_rate | AK1: avg_child_mortality_rate | AL1: avg_population_growth_rate | AM1: avg_natural_resource_rents | AN1: polity_mean | AO1: was_colonized | AP1: colonial_power | AQ1: colonial_begin | AR1: colonial_end | AS1: colonial_duration | AT1: tenure_days | AU1: tenure_years
A2: 1550 | B2: POL-1918-1 | C2: 8214746a-1e42-11e4-b4cd-db5882bf8def | D2: 290 | E2: POL | F2: =VLOOKUP(E2,country_continent!A:C,2,FALSE) -> Poland | G2: =VLOOKUP(E2,country_continent!A:C,3,FALSE) -> Europe | H2: Daszynski | I2: 6890 | J2: =IF(ISNUMBER(SEARCH("-", I2)), SUBSTITUTE(I2, "-", "/"), I2) -> 6890 | K2: 6892 | L2: =IF(ISNUMBER(SEARCH("-", K2)), SUBSTITUTE(K2, "-", "/"), K2) -> 6892 | M2: Irregular | N2: Regular | O2: Regular | P2: 0 | Q2: OK | R2: M | S2: 1866 | T2: 1936 | U2: 1866-10-26 | V2: 26oct1866 | W2: 13454 | X2: 13454 | Y2: https://urldefense.proofpoint.com/v2/url?u=http-3A__dbpedia.org_resource_Ignacy-5FDaszy-25C5-2584ski&d=BQID-g&c=kbmfwr1Yojg42sGEpaQh5ofMHBeTl9EI2eaqQZhHbOU&r=ZliGVSRwfirWoETOrKCh2RSnoygzVPWEk95Me9L-Kwo&m=EaKyFx9mpkhPdFxsxzvW_fiM3jbYwM3xYLjVbSFoDAg&s=8XEXIOEYa44vTzEptqHAqdRTZROWXXa4P9hEqNs51vk&e= | Z2: 1 | AA2: 1 | AB2: 0 | AC2: 0 | AF2: 1918 | AG2: 1918 | AO2: FALSE | AT2: 2 | AU2: 0.0054757016
A3: 1617 | B3: CZE-1918 | C3: 8217b290-1e42-11e4-b4cd-db5882bf8def | D3: 315 | E3: CZE | F3: =VLOOKUP(E3,country_continent!A:C,2,FALSE) -> Czechoslovakia | G3: =VLOOKUP(E3,country_continent!A:C,3,FALSE) -> Europe | H3: Masaryk | I3: 6876 | J3: =IF(ISNUMBER(SEARCH("-", I3)), SUBSTITUTE(I3, "-", "/"), I3) -> 6876 | K3: 13132 | L3: =IF(ISNUMBER(SEARCH("-", K3)), SUBSTITUTE(K3, "-", "/"), K3) -> 13132 | M3: Regular | N3: Retired Due to Ill Health | O3: Regular | P3: 0 | Q3: OK | R3: M | S3: 1850 | T3: 1937 | U3: 1850-03-07 | V3: 07mar1850 | W3: 13772 | X3: 13772 | Z3: 0 | AA3: 2.0999999 | AB3: 0 | AC3: 0 | AF3: 1918 | AG3: 1935 | AO3: FALSE | AT3: 6256 | AU3: 17.127995
A4: 1997 | B4: EST-1918 | C4: 8220a9b1-1e42-11e4-b4cd-db5882bf8def | D4: 366 | E4: EST | F4: =VLOOKUP(E4,country_continent!A:C,2,FALSE) -> Estonia | G4: =VLOOKUP(E4,country_continent!A:C,3,FALSE) -> Europe | H4: Pats | I4: 6630 | J4: =IF(ISNUMBER(SEARCH("-", I4)), SUBSTITUTE(I4, "-", "/"), I4) -> 6630 | K4: 7068 | L4: =IF(ISNUMBER(SEARCH("-", K4)), SUBSTITUTE(K4, "-", "/"), K4) -> 7068 | M4: Regular | N4: Regular | O4: Regular | P4: 0 | Q4: OK | R4: M | S4: 1874 | T4: 1956 | U4: 1874-02-23 | V4: 23feb1874 | W4: 20472 | X4: 20472 | Y4: https://urldefense.proofpoint.com/v2/url?u=http-3A__dbpedia.org_resource_Konstantin-5FP-25C3-25A4ts&d=BQID-g&c=kbmfwr1Yojg42sGEpaQh5ofMHBeTl9EI2eaqQZhHbOU&r=ZliGVSRwfirWoETOrKCh2RSnoygzVPWEk95Me9L-Kwo&m=EaKyFx9mpkhPdFxsxzvW_fiM3jbYwM3xYLjVbSFoDAg&s=Z8VLeAJDzsMikIwy1WxkA_aC2bDoaBhGCaAVPjFOc14&e= | Z4: 0 | AA4: 1 | AB4: 0 | AC4: 0 | AF4: 1918 | AG4: 1919 | AO4: FALSE | AT4: 438 | AU4: 1.1991786
A5: 1781 | B5: YUG-1918 | C5: 19777948-3bbd-11e5-afeb-eb6f07f9fec7 | D5: 345 | E5: YUG | F5: =VLOOKUP(E5,country_continent!A:C,2,FALSE) -> Yugoslavia | G5: =VLOOKUP(E5,country_continent!A:C,3,FALSE) -> Europe | H5: Alexander | I5: 6910 | J5: =IF(ISNUMBER(SEARCH("-", I5)), SUBSTITUTE(I5, "-", "/"), I5) -> 6910 | K5: 12701 | L5: =IF(ISNUMBER(SEARCH("-", K5)), SUBSTITUTE(K5, "-", "/"), K5) -> 12701 | M5: Regular | N5: Irregular | O5: Assassination by Unsupported Individual | P5: 1 | Q5: Death | R5: M | S5: 1888 | T5: 1934 | Y5: https://urldefense.proofpoint.com/v2/url?u=http-3A__dbpedia.org_resource_Alexander-5FI-5Fof-5FYugoslavia&d=BQID-g&c=kbmfwr1Yojg42sGEpaQh5ofMHBeTl9EI2eaqQZhHbOU&r=ZliGVSRwfirWoETOrKCh2RSnoygzVPWEk95Me9L-Kwo&m=EaKyFx9mpkhPdFxsxzvW_fiM3jbYwM3xYLjVbSFoDAg&s=hkCaRKRHNcAbMTxSSiT6HE4YSNHV1D49rupurgAtr5A&e= | Z5: 0 | AA5: 3 | AB5: 11 | AC5: 3 | AF5: 1918 | AG5: 1934 | AO5: FALSE | AT5: 5791 | AU5: 15.854894
A6: 2028 | B6: LAT-1918 | C6: 82216d01-1e42-11e4-b4cd-db5882bf8def | D6: 367 | E6: LAT | F6: =VLOOKUP(E6,country_continent!A:C,2,FALSE) -> Latvia | G6: =VLOOKUP(E6,country_continent!A:C,3,FALSE) -> Europe | H6: Ulmanis | I6: 6896 | J6: =IF(ISNUMBER(SEARCH("-", I6)), SUBSTITUTE(I6, "-", "/"), I6) -> 6896 | K6: 7051 | L6: =IF(ISNUMBER(SEARCH("-", K6)), SUBSTITUTE(K6, "-", "/"), K6) -> 7051 | M6: Irregular | N6: Regular | O6: Regular | P6: 0 | Q6: OK | R6: M | S6: 1877 | T6: 1942 | U6: 1877-09-04 | V6: 04sep1877 | Y6: https://urldefense.proofpoint.com/v2/url?u=http-3A__dbpedia.org_resource_K-25C4-2581rlis-5FUlmanis&d=BQID-g&c=kbmfwr1Yojg42sGEpaQh5ofMHBeTl9EI2eaqQZhHbOU&r=ZliGVSRwfirWoETOrKCh2RSnoygzVPWEk95Me9L-Kwo&m=EaKyFx9mpkhPdFxsxzvW_fiM3jbYwM3xYLjVbSFoDAg&s=5GenJdkFkhAPKjA4QxcYjNqG8XfHRTOpm7_k93yliQA&e= | Z6: 1 | AA6: 1 | AB6: 0 | AC6: 0 | AF6: 1918 | AG6: 1919 | AO6: FALSE | AT6: 155 | AU6: 0.42436687

Sheet country_continent
A1: Code | B1: Country | C1: Continent
A2: USA | B2: United States of America | C2: North America
A3: CAN | B3: Canada | C3: North America
A4: BHM | B4: The Bahamas | C4: North America
A5: CUB | B5: Cuba | C5: North America
A6: HAI | B6: Haiti | C6: North America
A7: DOM | B7: Dominican Republic | C7: North America
A8: JAM | B8: Jamaica | C8: North America
A9: TRI | B9: Trinidad and Tobago | C9: North America
A10: BAR | B10: Barbados | C10: North America
A11: MEX | B11: Mexico | C11: North America
A12: BLZ | B12: Belize | C12: North America
... A187: ERI | B187: Eritrea | C187: Africa
